{"type":"FeatureCollection","features":[{"type":"Feature","properties":{"adcode":110107,"name":"石景山区","center":[116.195445,39.914601],"centroid":[116.176229,39.933205],"childrenNum":0,"level":"district","acroutes":[100000,110000],"parent":{"adcode":110000}},"geometry":{"type":"MultiPolygon","coordinates":[["@@BCBB@@B@@A@A@AB@@@BBBAFCD@BAD@D@D@B@F@BAD@BBFBH@JEBABCBA@@@ABAB@BBB@@AB@AD@@ADF@DCH@@JH@@FJ@@B@@@F@@@B@@D@@@D@D@B@@BADH@ADFBDAVDH@@@@AB@B@@BBBA@D@@@A@K@A@BD@L@F@J@FG@@@@B@@@@B@@B@@D@B@@BC@@@@BBB@@@@@BA@AAA@@@A@A@A@@@@A@AA@A@@@C@@@A@A@A@A@A@@@A@@CE@@BAAABA@@B@BA@CAU@CA@@CA@B@@AAA@I@@F@B@@@HB@@DJ@F@@B@@BBEB@@@@BD@@D@@@@@CB@@AB@@@B@@@@B@@@B@@@B@@BA@@B@@@@@@@@B@@HAB@@F@@FE@BBABA@ABADEDGJGD@DADA@EBKF@D@BE@CDADBB@DAB@D@@BBB@@BADBB@BABABA@CBA@@@CD@IACIGCAA@ADALADABCAECGAABBDCDCHCBECEA@AA@@AEB@@A@KCWAIAIGBKDGFABA@ADA@ACK@A@BC@ACCB@A@A@AFEAADE@@CA@@CAA@A@@AAEACHI@AB@@ADABCHBBBBCDC@A@C@CBADAF@DAB@FA@ADABEDGFGHCB@BA@A@CBEBABAHABADCDEDEB@"]],"encodeOffsets":[[[118956,40847]]]}}]}