{"type":"FeatureCollection","features":[{"type":"Feature","properties":{"adcode":130684,"name":"高碑店市","center":[115.882704,39.327689],"centroid":[116.034663,39.259853],"childrenNum":0,"level":"district","acroutes":[100000,130000,130600],"parent":{"adcode":130600}},"geometry":{"type":"MultiPolygon","coordinates":[["@@IJKJCJCLARBZ@JDLENQJKAIJALFLHNHLDJDLELAB@BAHLXDD@T@NBPHZBVALCLEJEJCJKLEBE@C@@E@AECCAIB@DABK@AAKBK@IAG@IBCEG@A@AFGDAD@EACCBAB@BDB@D@BC@@B@BCD@@CAGBAMEIS@_ACJGBABMBABAD[BCB@BA@ABMBECA@AGQBCAAI@CQB@FE@EB@LM@IBO@@BABC@EGM@@C[@CE[JC@ADMBKDCL]AU@]@A@FJK@GDK@ACE@ABCBE@AEaDADCBEBEDOEAHIAU@@EA@@@AB@AC@WCAA@GA@@AL@FCAGC@@AHGB@DCAE@AC@K@AKBGAAAAO@BCG@CC@GI@@CB@@EB@@AAGBAB@FAAEJ@BA@ED@@GBA@EB@@EFC@AB@FCFBDA@A@EJA@BBDFBH@FE@BH@D@@BF@@DB@NA@CB@B@@HNAJBP@@DB@F@@CL@B@@DBAJA@DD@@DBBD@@GLB@GHBB@@@H@BAAGF@@@@EG@BCHAACA@[ICU@C@CDCBECBAGFBDCB@B@CFFEBCBCB@DCFABBFAB@AEH@HC@@JCNG@GCAABCACABEB@DABABCDEDDD@CA@C@CBAD@HCHAB@BD@FAB@DRB@Q@CAEH@FABAACJ@@GDA@@H@FC@GM@KAACAC@C@ABAD@@A@IAED@@CBC@KAAE@@CEgBAD@AGGB@ABC@GBEBCEQCIEOCKPERAPCHBD@BHH@B@BBBAFFFAAE@AB@DABEJCJCF@N@F@H@H@DCFC@@BDD@BBH@ADLCBBAPFB@EBAH@F@PAPEBFD@RARFFL@NEPALCRFJLNLJNHNDJCAEP@BFJA@BNC@DXCAGF@@BPBZBHBZGdQZ@"]],"encodeOffsets":[[[119012,40088]]]}}]}