{"type":"FeatureCollection","features":[{"type":"Feature","properties":{"adcode":140224,"name":"灵丘县","center":[114.23576,39.438867],"centroid":[114.207844,39.372378],"childrenNum":0,"level":"district","acroutes":[100000,140000,140200],"parent":{"adcode":140200}},"geometry":{"type":"MultiPolygon","coordinates":[["@@UAYDULMDQAQEUAU@SCICQGOWAIBMMEMCSB_D_AOOKKUGKIMCIFERCLEJINMJMHKHKAcAW@OCKICSCKG@eJQ@O@QJMN[BWAMGYIYCWDMHMNELKLIOKKECECIDIDKFOJWBKCIEEECGAEEM@MBQHEJGJODOG]@SJOFUBIASBOBMBOLKRHNALEHGJK@SC]BUDSH[DU@UAKEGIKUAQCQESIUAMAAC@ECMCG@K@IJKNKNINKPINIHGDGDMBEJGNIJCHEBICQ@MAOCQCMAOCMIKMGMMACCIFGBK@KFOBMBSFMFK@YBMFMFMDIBI@EJCXELAV@LLFPF\\^NRH\\HPADIBIDSDMFKFO@CBAF@BAB@BAB@H@FHD@AABAD@B@D@@CACHAHEJCHO@KDOLSdATDRHXHVCJEHEJGRANDRHZNPLFAF@FBB@B@D@D@D@FBDDFDBBHBF@H@FAFA@@DBH@FBH@DBF@H@D@HFFBDBDADABAFBBADCB@LCFCDDFDHBFBD@FABAH@DBD@BBD@@BDBBFDB@BFHBDDBBFBBBDAB@BBB@BBDBBBBDDBBBBBFAD@@@HAB@BBFCF@HABCFGDDNJPBBBDHNLTRRPCVAXENDBBDCD@DB@DD@D@B@FAH@@DBFBD@DAD@BBB@D@BDDB@F@DBJCBAHCB@BB@DBBFBBBBDBDBF@DAB@BAFBBDF@BDHAFABCBGFADE@EBCAAAC@CD@BCBC@A@EDCAIACBC@EBIDIF@DB@CDABC@ABEBDFJDDBD@DBBFBBDBBDD@@DFDAFGDC@@DCHCBAF@BABBF@FAD@@DD@FHFFDADBDCJCD@BFDBD@F@FDBB@B@BFDAHDDADB@DBDABBDD@BBDBJCB@FDDABB@FBD@FFDFBDBADBBHBBD@FCDGBC@ABCBBDDLANAL@PCLBXDPFHHJNPRRFJLfDF@H@B@DCJA@@F@DFBF@JDFAHFDBBDFBJAFB@DBDBBDB@D@DBBADDDAJ@HAFBBDDFHDDBDDFDBJDDDBB@B@H@FDH@BAFAD@DLHBDADDLBFBBDJEJIFG@KCaMCGCA@@@EAA@@CBEBAAQ@CNCDCHAHAD@DABAFADBD@DCDAB@BAFKL[JMB_EQBKAM@IFA@CFGPINEJGHEN"]],"encodeOffsets":[[[117158,40599]]]}}]}