{"type":"FeatureCollection","features":[{"type":"Feature","properties":{"adcode":140321,"name":"平定县","center":[113.631049,37.800289],"centroid":[113.763656,37.842501],"childrenNum":0,"level":"district","acroutes":[100000,140000,140300],"parent":{"adcode":140300}},"geometry":{"type":"MultiPolygon","coordinates":[["@@M@UGMCUC[EMBA@GFMDA@EBEACBMFAJ@PCFODIAQ@KBMGACBIFO@CBICO@CAIAGAAAASCMEOGMECECG@GCEEGBE@Q@KDMFGHKFKRKLEPQJUPA\\C^BHGHGDILKRCfAVBdARBNFTBPAJCPMHGPEJAZAPBHFDDBBRBH@H@DDBDAB@FBFFDBBHBLBVBPBL@LAHAD@DABAB@L@DAFCDG@C@ADIBIJCJDVJXFP@VBPBVBNHVLTJLL\\TXBT@VENEbKTI`OPIPCPBHFBJFbBHED@RBRDLHJNHRLPDLDXPFLDJAJCLMJKHKFKJBLAJGLQFQCO@MBKHEJELAL@LBN@N@D@F@VCTCHIVCNANEJILMHODORETAJEJENOTENGLGHMHGBABCBE@QCEBABCFKJCBBBL@HBDBDL@DED@HBBBHBDDF@F@FCFGF@DBD@BCHHH@FBBABCDIDEDGBGBCDAD@DDBAFAB@DCFCDOPKLGFKJGHCBC@CACBCBEDCAAAECIAGAGGIG@CACCCCCI@GCCCEAEEEEAACCCBCBEBIDEBI@GAE@CD@BBH@BCDBFADGDMDKBEBEBC@OCGBK@E@ABA@CAECCCEAAAAABCDADC@EACE@EBG@IFIAKDCIBM@YEK@AEEBEB@B@DBD@F@HANCH@DAFIBIBEHSBCLCF@DABA@CBE@AA@EDABC@A@@C@CAAE@AAE@CDC@GAOGI@AA@CBABADBFAD@H@DCDAH@H@B@BEPEDM@EGCI@O@A@KKEIIGICEGNUNKDCDCLIJQDKTITEFG@GCWGMGIWEKICG@ADGNG@KCKEAKGEGSEKQEUGAE@I@G@C@IDKDWDSB"]],"encodeOffsets":[[[116330,38735]]]}}]}