{"type":"FeatureCollection","features":[{"type":"Feature","properties":{"adcode":140781,"name":"介休市","center":[111.913857,37.027616],"centroid":[111.987966,37.017991],"childrenNum":0,"level":"district","acroutes":[100000,140000,140700],"parent":{"adcode":140700}},"geometry":{"type":"MultiPolygon","coordinates":[["@@AAEOAEIGACACAGIMCgESCOGKSEMIKIEKGEASEAIQIOIEMCOI@KBGKCEAM@QJIF@B@@A@IBCADGKGEAIEUGUIKCSCaGSIKEEAEGCIDKFIJGLGTEXCN@JBHEAICIAGBIFA\\EDFBNDLNJJJFPHN@BF@NAHABIDSIKEKCMJKVEV@T@HCLCDABCDABANAB@BAAGAC@G@AAAA@AA@ABEAAEACC@ABABAFAJADAHADAFBBBD@D@H@LEFE@EBOAK@AAG@ABAFAF@L@HAFA@CBADADAJCL@VEHADCFIRKNKLEJEJEFFLJLTHVELELFHNHN@PEPGV@LBRDFJHHBDIJGFEDGJDLHHNHFHBHBH@F@DGFIJKLIJGJEL@JBDLDN@RAZBL@RFL@LFHFF@TGHPRJH@HBLFHLDHFDFDSNIHKLAT@FDFDPANF@B@BB@@@T@BM@@F@H@XAPIXYXK\\CHILOLOFOHEFGDM@MAGIKEGAQAW@o@aBKDIFIDKFGBIDS@AB@@@R@J@BA@C@UA"]],"encodeOffsets":[[[114639,38072]]]}}]}