{"type":"FeatureCollection","features":[{"type":"Feature","properties":{"adcode":150502,"name":"科尔沁区","center":[122.264042,43.617422],"centroid":[122.280573,43.651865],"childrenNum":0,"level":"district","acroutes":[100000,150000,150500],"parent":{"adcode":150500}},"geometry":{"type":"MultiPolygon","coordinates":[["@@AA@OBGDAJAB@@AG@@CA@[AAEE@ABC@KBIKIKEBAADAA@BADA@GJARG\\MFCP_SKDCRKDARCBC@AD@DBRKDCJA@AAC@A@ACCBARDBGBAGC@@JCBIDKB@JBBAF@B@BG@AEAIBY@CCL@@BT@@AO@@AP@@AG@U@BC@CB@F@AGWD@ABEFSB@FACGFICABCCAIGCABCABIABBE@CBKBAB@DEDA@]CM@AA]G@DAFKP@DBHIBEB@BA@YAC@@BABCFQEQGAAAI@@AEAGAAQMCCMA@BCFSAO@@GB@@MJ@JC@CV@@FB@@HH@XAL@Ac@CPIDCAUCBA@GAGB@AFABA@AGAE@EBGDIDOFE@SAE@AABCFCBIBE@ACCC@KAKACAACD@HAHGF@HAFAJCBADGDAHABADCDCLCB@AACAIBIDA@BAHCHCJA@CBAAID@@M@CMAEBAADEBCEABIBC@CBOFEG@@CD@@KVE@DLELAF@@FHBABJBD@@AP@BC@CR@@EEA@AHB@@D@DEJBD@LBJF@BZF@EHB@BLA@AH@BCU@@AN@FADA@CG@EAQIICAC@A@EBAHAFA@EDYACAAE@E@C@EDMAE@GAE@E@CBEDCBABEDC@CBCDCBCBE@G@CAGBGBE@O@EAGCGCE@KAEAEAGA@ID@EGDCBCBQ@AD@DAD@FAB@FCJCBABED@HALCF@BA@A@ADE@AWDKBEBC@MCIAKAGACCACBCBGDADCFAD@HABAB@HCJABADEDAHBBADEHEHEFAD@@B@B@BH@FBB@FBFF@B@D@FEFCDEBE@AAA@EB@DE@A@BBB@FBB@BBBBHAB@HBFDB@F@JBF@F@H@D@L@F@BBBABMFALANABRD@HAD@F@FCFCFAHEDAP@JCTED@PAPBTBL@X@LDD@H@J@L@PCF@F@F@VBF@DAFANEP@H@NAL@T@XAV@RBD@PBD@HAD@DEFCF@RCPC@RAL@DLBJIDAJEFBR@BALAD@BABBLCB@HDH@D@@ABDE@@DL@FJHBH@H@JZBFHPBDDD^@DDBBDBD@BCBAFBJ@F@DABAHBDAB@DAF@BCDALBD@B@@BBBDADBBABCDBDBD@DBB@BDB@@A@CB@FBF@B@BB@BBDADCDAF@BDF@H@BADBDBFBBGJERETJBL@@HNRDDPFBBLBHDFB@JD@DJENB@ADC@ADAN@BI@BBHBLARBNBL@@BDBADABADP@BKNBDKDBD@FAD@DDH@FFB@H@B@BDDBJDD@F@L@H@H@LB@MHAJAF@F@PED@DBB@DAF@@BPBDDABCBPHHDJDlNNDD@FDFDDFBDB@AA@IBGDCFAB@B@RFHDF@DBBBB@FAHBBAACDAB@BDBBDAB@BDBBB@@EB@BD@JFDDF@DADCAEECAACANBDHNH@D@NBFDFBD@HBJBNDITI\\ITO@BHH@JBH@HBF@D@LDBBFHLHBBTJR@JBJBHBH@H@FDHBP@D@H@H@D@DBD@D@FBHBF@HBFDFDDBFBDLDBDBFDJDBBRCN@L@NEFCJCFAH@JDF@FAAA@AFCBCJEFAD@BBBDB@FAB@BBBB@DjAtC`BpDbBTBBHADAHEFCD@F@JBJHLVKDCBADADHAB@DCB@BDH@BCHCB@DBDHF@BH@DBFDDBNCLCH@ZDVDJBTHHBZJFBH@xK@@B\\A@@LCAADLD@ADB@BA@AVRCENA@BFN@@BD@EFBBAHR@@HGCEAA@ADDDDDFBLBB@FDBBCBCBWCEBA@@DFDHHDHBB@F@FADABECGEEGAACAEAC@C@CDEJCJABEFA@EAKGCAEB@B@BDF@D@BCDCBA@CAEEC@C@CBBBFH@D@BCBCBK@G@IBGDQHEBCDCBABCAC@GCAAABCJCDCDEDGBC@EA@AAGACCCC@CBADEHAFCBSHKBEBKCA@IDCBE@KEIGA@EBGFEDGDIBIBM@E@CACEBCDE@A@AC@IBC@C@AC@ABEBA@EBCAAKAKAMAOAOACBAFBDADCBOBG@CBBF@BE@MDG@IB@BBBLB@BADCBIBG@BBEJC@AHC@BBBDG@FJCBGISFCDA@@AIABGG@A@DCAADCE@EBKQBCEACAECACGGECG@ABABGKAB@JC@@JCBBDGBEBE@ADA@AA@AEBCBA@ECAAEACBACAMEBCBKDGC@AOA@PE@E@CAA@E@EACBAB@B@BBDE@BHBBBFA@CDJ@@DA@CF@J@BEB@FHBST@@HB@@EFTFNFDBB@FBBAF@DAF@BB@FBFABG@CBC@D^@@E@AFBBNFDABAB@DDBBDDHDBDPFDLFFDLDHHDJF@BKBA@`ZHFBBRTEBI@GAGCGBCFKDYGA@ME@ASGICC@iKQABUHCHIFGDEDODEBCAMAUMO@[BCAAABEcAEAOCWMYQQKQU@ECAI@A@E@AA@AAI@HWBED@DAACACHABIC@ABC@CDE@E@AGaCGAKD@FEDE@@C@@BG@AIAK@@AC@E@G@GACACA@AGAC@IFEBADADE@AAGCBCAEC@C@FCACBG@AGQCCCE@EFB@AG@CBEAAAEAMCAAAACA@@AFKBQAG@GA@BBBA@EH@@GAC@M@CAE@EAECFECCB@@ADAH@BCKADAB@F@ACACC@@ABADBBBEGUSHIGCDKE@DCEC@@QECBBNGEBQGAAKBGB@@CBGBGA@BCBA@ABC@EF@@CCAK@CCI@@@GA@@IA@ADCB@BKC@BGD@@AM@AAK@DIE@AAG@BEBEM@BEMABCB@AABAJBBQcCaASA@GIAAHO@QCI@AJCTAH@BCRAHGFA@@DD@@D@J@NH@ABABAFAB@BABCHUAB@A@KD[GCLCAADB@ABA@ECECQCBC@@WGUDA@CDIAE@CDBB@BA@C@CAC@EBIAGB@DCBA@ADGBABABADGDAFCF@@CJCFCAEL_HEBIBADAB@DI@CBA@@CAAGAC@OBMDE@KBK@@A@ACACFC@EBI@E@CA@CAAG@E@C@CAEAC@ACCA"]],"encodeOffsets":[[[124733,44845]]]}}]}