{"type":"FeatureCollection","features":[{"type":"Feature","properties":{"adcode":150721,"name":"阿荣旗","center":[123.464615,48.130503],"centroid":[123.164072,48.633144],"childrenNum":0,"level":"district","acroutes":[100000,150000,150700],"parent":{"adcode":150700}},"geometry":{"type":"MultiPolygon","coordinates":[["@@WPUBCEOCcBkCKQSIeDWCeB[R]JgROAWWM@MJ@NMBcMSYSGuD]XOEaBICIRSTWHYD]JYDiAULSVALBLYOGOAGNCROPCLBVHZ@RLNJVIdHLEPSJkRWPQNGRALW^KTONOH_JQJON@JFRAPY\\CVU^EJQVANJPTNJNCZDJJTZdANYVMNU\\MLeRGJETaVQNCRFXHPNjCJUZYE]BYHSNWHmCUDSPCLSRSLMGUOWFMTKJYCeQ_E_PUNcfCPKTQPCRNPLHBJANMN_HaCWDMJMRDXEPU\\@NQVgCsASB[@O@QEQKIKWE[\\]PcLSJSCUGU@OCGE_KGSEkWQMKQiK_QUEQ@KGISKGYOOQ@KQ[EG]FU@]MYAQHQACEKWKGWIQIW@OEMKOKcaWKUIEGESKIOC_ASGkUSM[eJQGOQOoS{EAMHKKO[AUGNOCEOCSB}JYGcSCIXQPU@QQOE]LSAIKK]K]Ei@mGQI_MMKeMY@QFSDgMaAiNaAgNgTELWHUJYDWFOAOGAEJ[FK^QDQ@IFMNSJGREbH`@RKRULOCWJIXQBMDIRKBGVgFQDKCOGODMNKN_XBjKLCbE\\K\\ARBpMPIFILEXETDbINIHARRLHV@^OlA\\ARCRGVCNEhENCTJXRPJRBRAREHEE]JKJCdBVILKRARLLBbSHONM`IbSlGPBRATSBQOUDgUgCqDMjktCLEbWPWLERCHE@SNa¨^SfoF[^kKcCCH[A_CALKDaLIHWhcNE~@KSYC_VUBWJI`OLOdMZUlEdQhKdYjIT@\\LL@TK\\CXGV@FJHBLCHBRAJFhKP@FD`JJHNAnHjNNF^JX~PNFTTfVNLJtZVx\\fZV^bz`XNh\\PNVPD@XRxdzTHzTR`ZRN NHj^lbLJTH\\J^NlXn\\^R`P¢vd^J@"]],"encodeOffsets":[[[127247,49702]]]}}]}