{"type":"FeatureCollection","features":[{"type":"Feature","properties":{"adcode":230206,"name":"富拉尔基区","center":[123.638873,47.20697],"centroid":[123.590228,47.222379],"childrenNum":0,"level":"district","acroutes":[100000,230000,230200],"parent":{"adcode":230200}},"geometry":{"type":"MultiPolygon","coordinates":[["@@CBODMBKIGEAAA@G@SGGAGHC@BQIBEB@CACIFABEDA@IAOCC@MCGAE@OAQAC@GAOAG@EAABABC@C@EAA@AAAC@@@A@ABADCNGPIFCFCFCJGNGDSBMBKBCF@H@BKB@D@BBDBLJ@BBA@AAECKAK@@FILMDEXAH@FAH@FAXC@AB@D@B@@A@AA@@AB@D@D@DAD@@@B@@AACAA@A@@@@DAB@@@DC@@@AC@A@A@A@@A@@BC@@A@@@ABA@AAAA@ABAD@@@@@AA@@@AFBBA@@AA@@@AB@BBB@BAB@@AA@AA@AD@@@@AA@CBA@@ABA@@D@B@@@@@AAA@D@B@B@B@@B@@B@BA@A@@B@B@@@DA@A@@AAAA@A@ABAD@@@BBB@@A@AA@A@@@AAAAAGB@@AD@B@@ABABADAB@@AB@@A@ABA@AA@@A@@D@@@@AACACA@CAEAC@A@CB@A@@@AB@BAA@AAEAAAA@BA@@@AA@A@BCBAAA@A@@J@@A@A@AA@CAABAA@@BABADA@@@AAAA@@A@AACBAB@BBB@@@@A@AB@DBB@@@BCBA@AA@C@EA@A@CDABA@@ACAAC@A@AACAA@@BABA@A@AAA@CBAA@@@CAA@A@ABAFCD@@@BBBBB@BADA@AAAMCQEQEIA@ADA@@@A@ABABABCBC@A@CBCB@D@BAD@@ABAACB@BCBAB@BBB@@@BA@A@A@A@AB@@AD@D@BABAA@@A@AD@BA@@B@BBB@DBBABADA@A@A@A@C@ABABAB@@ABAB@BAB@BABA@A@ABABCB@DC@@B@BBFBBBBBB@B@B@B@@ABC@AD@B@B@FBBAB@DAD@B@DBDBB@BBBAFA@@BB@BF@DBB@B@HKJGLG@BBBLLHHBF@FCH@BD@F@L@F@D@@@@BB@LDHBBBB@DDBDBF@DB@DB@BBD@BFBFFBBBB@B@D@@BBB@H@HAEBGDED@BA@@BBDBDBB@B@BBBBB@@AD@@@BDF@@B@@@L@B@FBHD@BJADADAB@BBBB@B@B@BB@D@FAD@BBDB@@BBB@D@F@@BAF@F@BEFCBIFMHA@@DAD@D@B@BB@@B@@DB@@BALAXEJALAPA@B@@@BB@@BABABCBCDA@ABCBE@A@ADA@A@@B@BDBDFFFFFBB@BBD@B@@ABHDDBB@@BBBA@CBGDGDEDGDABEBABAB@B@DDD@BBB@B@DAB@BABBDBBBBDDDD@B@D@BC@A@C@A@CAC@CAE@C@A@AAEAA@C@G@I@ABEDCDCJAFBDIDIHCBCBCAECCCA@EBC@CBC@AA@A@A@@BCBABAGEAA@@CAABEACA@BC@ADA@CDA@ADEHB@CFBBAD@D@@A@AD@@ABAB@@CACAIAEA@@CHABB@ADEFA@CFCH@BCJIZ@BAHAD@B@FDAB@HD@BADCDADJHBBE@@HBFJC@FFDDDABDD@BBBMBABDD@@D@@BE@@BBD@BA@A@BBMFDFEDA@ABKDIIIJCAIBOFA@QBC@"]],"encodeOffsets":[[[126527,48499]]]}}]}