{"type":"FeatureCollection","features":[{"type":"Feature","properties":{"adcode":230904,"name":"茄子河区","center":[131.071561,45.776587],"centroid":[131.464111,45.887993],"childrenNum":0,"level":"district","acroutes":[100000,230000,230900],"parent":{"adcode":230900}},"geometry":{"type":"MultiPolygon","coordinates":[["@@DDBBBFBDDBFBHDJL@NBNDDTJH@FAJAD@FBFDDJLLNFBBBFBBF@BDBDDFDBFFJN@DBHBDDDZL`RH@b@DBFDDBBD@DABEBG@SBC@KFGHCH@FBHHFDD@JBDDFBD@BCJ@D@DBDVNJLBF@DADCDaNO@Q@eOOGIEAEAAA@IBK@E@CCEGAAeDgDGAEAKMIAE@EBCFGPGFIB±fEBAFBLAHELANAn@f@FBDDBdNLFDBDDBJAHEREHCDE@C@IAG@C@QFaFYFKFIDGAGAEEGGECE@I@AB@FALBJGCGCOIECIE_EQGOIAEBIHu@EACIGKCQCEC@IAKGCKA]CZwOH_EacFaHW[Iu_SUUG__SeGYAuUWQJOM]VqaWAYGgGmq@GDABCH@DCHADCFAF@DFF@BGCC@CBA@AAAAC@I@EDGBKBG@GBEDEDEBG@KBG@GDIDABHLDDDBFHEDC@A@AAGGKGGB@@MKGEEEAACA@CCAECCAC@C@CDCHCFCFAFIHABA@EAC@C@A@CFAFCDCFGFAFCFCHADCDC@EAC@EBC@ACECC@ABAH_nABBBC@IEABEAKKÙ¯GAsOqODEFGFIBGDEDABGBM@GBCBABCDEAEBEBEBCAEAACAC@BAD@JANIJCAACCECACC@CAAAAC@EBC@CCAGCEAE@EAECGCGACAB@DG@AEC@A@ADE@C@CAAAECADAHCB@@C@E@AACBCBADAJA@C@K@CDEHKBABAL@HCH@FBD@FAJ@JAHAHADBDBB@DCD@N@D@B@@EBEDIB@DBJBFBHBH@D@B@DDD@NHPDNAHDDEBCDADADCBE@G@CBAFAD@DADALEDABABDBD@FAF@B@BJD@DDBJBNGB@FBBAHEBAFAFIBIJAB@DDFBJ@HBJ@H@H@D@DDJ@F@FBD@FBH@FBH@DBLEBA@AEEAE@ABE@AAACAACB@D@HCDADA@GFABAF@FAD@FB@BJPBBD@@D@B@FBDFFHFHDBBFHFDDBDFAD@BBDBLBBHDBBF@DADBDDDDDF@DAFBDDBHDBBBBD@FB@BDB@BABC@GBCBEBO@ABIBC@C@A@CHABAB@DDBDHBBFBB@DDBBADDFDBD@BDBDBBNBFDFBFDHBD@BBJBDBBBBDFDDBFBHED@DAD@D@FAFADBD@DDDBJBB@FDD@HAD@F@HDD@D@FA@@@DDBD@DBBADBB@D@DCDCB@FBB@DAB@BBD@@B@DBD@BEDAB@DAD@DBD@BCF@BBBAHAD@DBFFBGDABAJCFAF@BDD@BABCFCDCBEDCBABCFAF@JCF@F@H@DAD@BHBBBF@D@DA@DDBDDDBBBAD@FBBHBDBH@DBDBFDNFBB@BABDBJD@FCDFDFBBD@B@B@BBBDD@DEBCDAB@BBDD@F@F@B@DDFD@DAB@@DDB@BD@FBBDBDBF@B@BCB@HDFAFAJAD@R@DBBBDBADHDBDFB@HAB@DBB@F@BBJDD@H@BFFJDD@LALAH@FBDDDDBDDBBDBB@@DCHCBGDCFCFCB@P@PAHAB@HBD@J@JDF@D@DBDDDDDBB@FAF@BCAGBCBAJEHBF@FBDBD@FD@BFBHBHBB@FBB@B@DC@ACCBCACCAACBCDABCCC@ABANEB@FADDFBLBDBBB@DFDF@FAJCD@DDDBFBB@FC@@BDDDF@H@D@B@BCDAFD"]],"encodeOffsets":[[[134952,47006]]]}}]}