{"type":"FeatureCollection","features":[{"type":"Feature","properties":{"adcode":320411,"name":"新北区","center":[119.974654,31.824664],"centroid":[119.886314,31.924334],"childrenNum":0,"level":"district","acroutes":[100000,320000,320400],"parent":{"adcode":320400}},"geometry":{"type":"MultiPolygon","coordinates":[["@@B@BBB@FB@@BBB@@AA@BA@@BA@@@BB@BBA@A@B@B@B@@AAA@ABABCB@D@BABDD@AABABDAABD@@B@AAB@@A@@@DBDDFB@BADABBBBABBB@A@BBB@@@@@BD@ABD@BA@A@A@BDB@A@BDBB@B@F@BAB@@A@@B@FC@@@BDAB@BA@@DDB@BF@@@BBB@BC@BB@BHJ@@DCBBDA@B@BABBBEFFDFAHELEFADHJPFJBDBBFH@B@@FA@ABC@AB@JAF@BBB@FAD@BCBCBEBA@@CEDAB@B@F@DABADEB@BAB@B@B@BEAAACBAAC@CAE@ATGLCFAHABDFA@@@BAHB@HBBAD@HAFBB@HCBC@@@AF@BABGBCFADBHHDDHFFBFBD@F@HBF@BBDDBD@D@BABABC@@B@BADAB@@ABBBAB@ACB@D@T@@EABF@BAHEB@BAB@BE@@@A@ADCD@D@@JBLDDBB@BFBBFB@D@BB@@BB@@BB@BBA@BBB@@BED@@@DFJDBEBEBADCHA@C@A@ABAD@@EDFHBHB@ADADJJ@BTFNJCDA@ABB@ABGHEDABCFAF@BBFAF@D@FBHFDHDNXKFURMJe\\ITEAQ@QCCCA@C@A@]DM@GAG@CBA@EDIJADCDADEPEPCHAH@DBF@@EDCAA@CCEGEA@@IFELELEH@@GCKIABQLCBGB@ACAACAA@AKAKAEBGF@@a@A@EAIKO]IOGSCEDAF@DA@A@@CAAACEAEDC@AAC@@AA@IA@CA@G@ADC@AS@C@@HCF@DAHIDKHGFE@CGGCCoNACDACCbKLCAE@G@CBC@@AA@@QAIKGIII@@ID@CDIRO@K@QAA@@NSB@NDJFbBRAH@IMMWGEGECA@@@I@AEAACAABGDCDCBA"]],"encodeOffsets":[[[122667,32572]]]}}]}