{"type":"FeatureCollection","features":[{"type":"Feature","properties":{"adcode":341222,"name":"太和县","center":[115.627243,33.16229],"centroid":[115.641424,33.331497],"childrenNum":0,"level":"district","acroutes":[100000,340000,341200],"parent":{"adcode":341200}},"geometry":{"type":"MultiPolygon","coordinates":[["@@@@F@DFDBDDLFFFBBJDRFFBLDDBDDFBJDLHBFDD@DDHBD@HFNFDFBDBLBFBFBJ@DDFFDBJEHGDC@EA@ECEG@A@ADCB@P@FABCDQDGD@B@DBFHDDFFDBBADADEFAHALEREHEDCFAJEBAjLHFPFJ@DJNLHJHFLDB@BHADH@FBF@CDEF@DBFABEFCDBBDBFDHDDBHFJ@F@H@N@^@@@DAAEHCBCDBHBBXBDF@@HF@BLJHFDDPBFBF@DADCDELCFAFAD@HCFAFADAFAH@L@F@LDH@JBBJFBD@BBBNCNCHCPKFAJAJAJEHEFCHIBADCTODCHGBAHE@BBFBDBBFB@DDBDBADADCDADAHCFABMDADAHBB@FED@FDFFFBBADCD@FBDBDHFBF@JADCDAB@DDBNDHBBBDACJCDDJABCDC@CBBDBDAHBDCFCDC@A@ABBFABCD@BAH@DGJEDGLCD@HAJABDJ@DAN@BCB@DDFBDBHADBDCHCDA@CB@H@BCDCBGDC@CFADIJGFABEHEFKLCBADCFADEFOBGBGAC@A@CBCFC@ADIFCBGFGBCDI@EBE@ADCBADEFCDAFKDGBE@ABEFAFIDGBA@IBEBABAF@@EBCBGDKDABKDMFC@IAEAKAKBE@ECGAE@KACBEDINGLILEJEJADCDEHAJALEBAFDDCHId@FKAaC[GE@QAUAG@Y@AQAEAAECC@CBCFC@E@K@CAICM@EAEEIACAEECAEBEFCBAD@FABABEAGAIEGAOAEACBGFADADADC@G@IIC@M@WEWCGGCCAEAG@EAECCCAC@AAACDGACCAECFMB@EOEGJERKDCFG@CBCECEAEAQAEAEEAEBEFEFCDCFCBAHCDCDANIJEDAFIDC@CRGFB@CAEGEAKEA@MGE@CFEF@CKZ{@EAcFE@IKODE@IAMF@BAEUBQLC@IQEBEE@AGBAPA@CCE@EBG@GEKECCCIGEICEDIBCDGHQDEDADGDAH@@E@@AIA@AAA@@ABA@ACC@AODIKCAACCCEKCE@G@MFEDEFE@E@IBE@CBCFEFAHADBF@DBH@RCLEPABCBEAAGCDIHQBCDEBCFEHGDAPGDCFANEHEFAHCJA@GAE@G@CCC"]],"encodeOffsets":[[[118300,33869]]]}}]}