{"type":"FeatureCollection","features":[{"type":"Feature","properties":{"adcode":350125,"name":"永泰县","center":[118.939089,25.864825],"centroid":[118.78949,25.852196],"childrenNum":0,"level":"district","acroutes":[100000,350000,350100],"parent":{"adcode":350100}},"geometry":{"type":"MultiPolygon","coordinates":[["@@@ABCBEE@CAACBCFAFCBA@A@ADGBCDIDC@CBA@A@AAACAAAE@CEGGGCCBGDC@AEAE@A@C@C@A@AACAG@CMOGG@EBADCJDD@BCJMHELCHCFIDK@GDK@AACBC@ABCBADAFEDGBK@EAA@C@C@C@CBC@CBCDEDCFEDCDCFADCDAD@B@JFDAB@DCBCBAHEFCF@DAJCD@BC@C@AJGFCBADA@C@EBABADCD@BCDA@CBADABABBHEBADEBCFEBADABA@CBEB@DAFBN@F@HDDDBB@@CD@BBDBDPNJEVLJMD@DBDDIJ@DBDFBFADGDGDBDH@NDBHBBAFKBCHBFBBH@HAH@DDB@@FCDB@@@DCJ@FDBD@BA@A@CBCBAHADCFCFADBD@BB@D@D@F@BDDBBDBF@D@FBP@NAPCDCBABABADABA@@CCCAAA@AFCNANBF@@@@C@CBADAFCBBBBB@@A@C@ADAB@DADABBBDDDB@B@D@D@DFLHDBDA@C@IIYAEBCHAF@FFFHDFB@D@HBJHDHAHAF@DDBDAFEHGJCNAJDDBNFFBJFDDHDDFDFBBBBBB@BABCBC@@BBDJDDBBBDFFAX@BCFGFCLG@@H@FABCNCD@DDHBDBF@D@F@BBBBF@BABAACEGAC@@BABADB@BDDD@BBFDDFBBDBBB@@B@BB@BBBBBBBBBBB@BBB@BDADBBBBBD@DBB@DBD@DBBBBAFBBF@FJJDD@@BB@BDFBDBBBBD@DBH@@@FFBB@B@D@BDBBB@@HDD@DABC@CCAA@C@CC@G@CDCBABC@GBCAEACAC@ECE@G@G@ABCBBFBHDBF@BDDNDDHBBBBBBBBFB@@H@LCDDFDP@P@NBBDHDFBFDF@ZAHFFFHBJ@FBHBFBB@@D@BB@DD@@ABAHAD@D@B@FDHBDB@DABCDEBAF@DBFF@DABAB@DDBDBFADBBBBFADBB@BFBB@BFFBD@DAF@HDHDJBD@B@@CBABAAA@AHAHCFCD@FFFBB@FCDAHADBFBDBBBFDHFHFBDAFAD@B@DABBBBFFBDBD@HBFBLBBBBDBFDDNFDBBFBBD@DBD@B@DBDDCDCFEJGBIFCFCJ@N@BFFDL@BAHADEBEAI@KFGH@N@@G@C@CAC@CAAAEAAACDADAFCDCBC@C@CAECEGCCEACAEAC@CBCBCACAAB@BDFJDDFADCDE@G@CDEHCLAFABCBC@ABAHBHDJDJBLDJDFLDDBADCDCDGBECIEICE@CD@HBFBBBBDFBFFHFH@F@DIDGDADADABC@A@GBABAD@BCFEBKBGBI@KA@@IFGHKDKBGCA@CBADEDC@E@EBC@IBECCECBCFCDAF@F@DADABG@KEWEM@IDCD@HADG@KCGDIHKFGBCFAFBFDF@B@DBFBJAFADGBEACAECE@KDG@CAECECMEKEE@GACCG@GFGDEDAHGBGB@@KFGDCBC@CCCAI@AC@CBCFC@C@G@CAC@@CCC@E@AA@A@CDEBIBGAEACEAA@CBEBG@ECACAE@EBABABA@AAA@CBABCBA@CECCA@ACAI@ABGBE@CBE@C@ACAK@@B@BA@AAAA@ABAD@@CCCAA@A@E@CACACECCCCAA@CB@FC@AAAACAEAEAI@ACAEAEAEC@CBA@A@AAAAAAACAAAAA@ABEBCBABEACACAC@C@@D@BA@A@A@@CACAAAAAAA@@@AAAC@A@ABABA@C@EAC@C@@@@B@J@BC@EDADABBDBDD@BB@@EL@D@F@FBDBDA@C@C@E@AAACACA@CCBGAC@ACA@@BC@A@AAAC@CBEAGACC@@A@E@A@@@@BBB@BABAA@@AA@@G@CBCB@B@D@BADADCBCBA@AAAAAAC@ABABBF@DADCDCDEBC@AB@D@D@BB@BBAD@DABA@A@CCCEKEACA@@B@BA@CAAACACAA@A@CA@@GAC@IAKEKAE@ABCF@F@DDHDNBF@B@BGPADAF@D@FAB@@A@AAAE@CA@ABAB@DA@CAAAC@AB@@BD@DAB@DADC@ABAB@BADA@C@A@A@EAAB@DACCCAECEC@CBAD@D@DA@AAEEEACAG@A@CCDC@AAACEACCAC@C@CBEDCFA@A@AAA@@AABCDABA@C@EBAB@H@HAFCD@BCBCBE@EBAAA@C@@A@KFABC@E@EDKAGCGAACI@@@ADAB@@EBABABAAA@AAAAAAC@@ACBABABABADA@A@AAAAA@ABC@AAAAC@AAAAA@A@A@C@CACACBED@D@@@BA@C@ECCCCEICCAE@A@CBEAAECBAB@BA@ABEBABCBCDADC@A@A@@CAC@C@BBADGNABC@E@C@CBABE@G@EBEBABCDCBC@CACAEEACBEB@B@BE@A@CBABCBA@CAQ@CACCCA@G@E@A@EGA@@@AB@BHp@J@DEDEBEHABADABMJMLCBCBCCACEEEGCEGGCEBCBEACE@G@AAAC"]],"encodeOffsets":[[[121252,26511]]]}}]}