{"type":"FeatureCollection","features":[{"type":"Feature","properties":{"adcode":360603,"name":"余江区","center":[116.822763,28.206177],"centroid":[116.913619,28.314635],"childrenNum":0,"level":"district","acroutes":[100000,360000,360600],"parent":{"adcode":360600}},"geometry":{"type":"MultiPolygon","coordinates":[["@@JMFIBGDGDQFIJEHIFIDG@GAKCGAGCEAIAEACCE@ECEEAI@G@EBKDGBG@K@G@EBEDCDIDMDQ@GAGAICOGKGKECEKIGIEI@K@I@IJIJEFCHAH@J@FCLDF@DC@CCGCEAK@CFGFCNAF@H@HCLGFAFBJDTBLFV@HAHAHCFEBE@GAEAGGGCECECIAE@MAM@EDEFGDCHCBEGEBEFEHAF@JBLFHDBBNAH@HCFEHGFCJEFEJALCHBFEHGJIHEFAFAJ@H@F@DDDDBFBHDHBDBHDFBDF@DABJFFBBDBF@H@D@FNDFBBHDD@AFJJFIHCBAJEF@D@BB@BCB@BDDFADB@ABBDFBFFDDBAJBB@DE@C@CCADAFBDHF@DBBABBBJB@BCDABBJDBBD@FBDCFABBDCJELCLAHCLCF@HDJ@HBFDB@H@@AF@@BHABDL@@BBBBAB@FADC@A@EBBBA@ADC@@FA@E@CFBBJ@DBHFAHC@AD@BBFCB@DBBBABBDBBCFAD@B@D@DCBAJCFBFCDADD@BFNANCRCFCDEBE@M@GBGDGPENCHAD@LAFAFCH@D@FDBBBBBNFNFDDHHDHBJBP@HAJCNAH@JBT@LAHCFGFGFCJDHFJFHFHDDBFBPDHBFHDHLPNLHHDHFD@HAFCDCBAH@BAAGB@HAF@BBDDBBBBBBDABA@CAAAEDAL@D@JAH@HAD@DFADCF@DB@FABEBBBFBJBDJFDB@AAE@ABCD@@HBDBDD@FAD@HFBD@P@FCH@F@DDBHDBBBH@FBBDBH@D@BBBDHDHBF@@BAFBBDB@LBJDJBHGHEFIDEFGDEBIBMBKFIFGFGDQRCFCFGFGBMBEAKCIEGCEECEAE@IBIFIFMDI@GAECKCGCEKMOO@GCCEAICA@IEAACECACAAABADA@ACA@A@EAACEE@AC@EA@CDADAJC@A@AAADBBADCBE@ADBBADADADCJGHCHEFE@C@GCAEACICM@GBQCMAI@I@EAG@EBECIMA@AADEC@BABCAAAEOCSFGBEBCC@C@MBGFKDGFGHIHOBEBCAECES[GGCEMMCOACAIDEBAJOFCBG@C@IACECGEG@ICIAE@G@O@MAIBE@GAMIMKMIKIEECGEOCC"]],"encodeOffsets":[[[119592,29022]]]}}]}