{"type":"FeatureCollection","features":[{"type":"Feature","properties":{"adcode":370724,"name":"临朐县","center":[118.539876,36.516371],"centroid":[118.551234,36.36],"childrenNum":0,"level":"district","acroutes":[100000,370000,370700],"parent":{"adcode":370700}},"geometry":{"type":"MultiPolygon","coordinates":[["@@BIHCBECEHAHEBGBCFCD@DCACBIFADADCAK@ADEHAACFBBFDBDEACDDB@JAA@CABAX@JBHADEIGIGAC@AF@F@HCFABC@EFG@EBENECEAEEC@ADCLIBKACGEDCAEBIACMMAE@GFCJAF@HDLHRDNJPBVMBA@CDEHCLAJCDCDABADA@CACCEAABCBA@GAE@CBEEGBMAAMGA@AEB@FA@@DEACHKDG@@DKDGL@B@BCAIJEFA@ADO@K@CD@AEBC@@GCA@ACDE@GJBDEHCF@B@DBHA@AAADAFFBDDFBAFBJ@F@BBCD@DNHD@D@HEBAAEFCBB@DHJHADA@AJCF@BCACD@DBF@B@D@DAACFBDABCIGEAIGAADE@CACDADCBGACIA@EDEBE@O@CAC@KAADADALGHBDAB@HDFCB@AFDBBBDDABHDXN@JDBF@DHGLCDFD@BUDQAE@ABC@CFABBBD@FCF@@BDBBFHGBAHBNDDFHDHBB@DFCDJDDADA@EB@DLDDDBJDB@FADBBCBBDLCHCF@DBDDFHFDHB@F@B@AC@@HED@RFLLJDF@DDLNB@FABBFJDBB@JGD@NEB@HBBBBDBFJ@HANGB@FADCN@FBBCFEDKBAB@@EEC@CDADBHC@ADBFA@GBAHAHBDNBBHDLBBAJCBCAG@E@ALADFRFGJ@DDH@FALBBFBFABCBDF@AHDDBBD@BBA@@BBJBDADCFAAA@CBBHDDABAD@FB@EJA@@BEB@FBBHD@FABH@BFFNDHNLCDBBBL@F@JLJD@B@BBADFFLJD@BL@N@DD@FHDHFF@FADDJBDBDADABKBYSCAC@AALABGACEACBAA@CCAGAEECECBMJ@BBNDFQBYHBBH@B@FF@FJ@@DDFCJAF@PIA@PANKHA@CBBBBFABAAIB@B@DFFJBXBLD@BABC@@DD@@BADE@AFAD@D@DGP@FGF@D@BL@H@PEBDFAJAB@BF@DHAPKNEDCJO@AJARIBBFFAH@FEHABCDBJBBJFD@B@D@@DCJED@HBB@AFA@FADC@@DLPH@DCB@BBH@F@BB@NEVkFK@MDKCSHHNAHGTEJ@NOHEFDABDF@EFHABJD@BJJRJLFNBP@\\AJCNS\\KHIDMFWAA@@FI@BFCAAC@DACKB@AEBAA@AF@@CE@ABCE@AE@@CC@SBMDMHKLGLENINCFKFQHGHIHE@IIGIEAWBUJGDSAYDM@G@ECAEFM@IEEEGGGGMBIDKDEFBFBDBDDJABAACDEACA@CBA@CCAAAAAEAACEA@ABC@CAC@KDUGICWACAKIKWECE@c@OEO@MEQEQE]GGEOIEAGAE@EDABEBEDGFABA@C@CECACAEEEGCK@CHMCCKCGKEAQEBACCGEKEECOEE@CCGGACKCQEICMAECEICIYNIBEEGEIEBE@ECC@CBEACQCOAMEEBAA@AJ@HE@ACC@ADCBGE@CAGGCIAAGC"]],"encodeOffsets":[[[121074,37263]]]}}]}