{"type":"FeatureCollection","features":[{"type":"Feature","properties":{"adcode":370703,"name":"寒亭区","center":[119.207866,36.772103],"centroid":[119.141523,36.996913],"childrenNum":0,"level":"district","acroutes":[100000,370000,370700],"parent":{"adcode":370700}},"geometry":{"type":"MultiPolygon","coordinates":[["@@BD@TADAH@L@BFPBFAD@FAB@BBD@FCD@FA@ADCFCFIFGBIHAD@DA@AAGBIDC@AAOICI@GE@G@ECEGAEG@C@CM@A@GMEQ@IDCFC@@DADC@@BABI@@FGBBFCBC@ECIDAHA@@DB@BBNFBFF@AHC@CP@BCC@BE@@BG@@FD@BD@DAHBHCF@@@FeB@CE@AA@CC@@SAAG@ABGBIGGAA@AABAACE@BDA@OBGACBCJAAA@ABAFGAOBK@@PKBCDCDAD@H@HA@CHBFDFBBF@B@DFHFANGDAHG@IDEF@FBBB@@ABCD@BDBHGBBFD@BEFADBBB@BEA@BAHBDCDAABCA@EFDV@BE@DHD@D@HBDFBDBR@F@DBF@BFVBR@DPZBD@NAHBB@VBL@D@B@FBF@H@HBF@DBHDPBJBX@D@NBRAF@BCBCFEJCD@FAJDJBDDBHDHDJNBD@J@DDBF@DD@FBFDDHFBBBLJ@bTABAFAXAHCDGHANBLJ\\DNCNKJOFQAYGQBOFWVUFS@KCCI@ODWAIEAKBIHDrBHDHN\\BF@D@BCHCDEBKCCBBHl\\ON¹G@CCCGE@IDAFDHL\\JRBH@V@FHDHBLADARMD@BBBDADMPEBCBe@ECAI@YAKKQgLSBOGG[EGKAWFkeGIUOSWeCu@MAOP£Ce]@DwvBD@CwFQVIZCPEFKFSVCPFHBDABEJ@HRJJTBbBVJJDHDTM\\A`AVBHBJ@DCH@RFBEAECCKCACOIIID@CKIB@@AE@C@EB@@CDA@AC@@AHA@ADADHLCEICAGCGDKDDHE@AEA@AABGAGAAAGA@@CG@BEC@CMC@@@G@@BE@CDCA@CGBAGBAACAGDA@AJ@BJJFD@@CD@BDD@@AH@EEE@AAM@@EB@NBACB@FJBAAE@CA@@GB@@CBADAACE@A@NEA@IDACFADCAAOBACG@BMEACHG@@IC@Q@AAAACAA@EGDAACCA@E@CGAEGEIEECAG@CEDCDA@A@CACEAKCECAE@KD@AEICAE@EEKBADAD@AGH@BGD@BA@ABKF@@CBGC@@AIAC@GCACBO@ABA@CDCHC@EBAACAG@C@ECK@CAM@CAE@CAE@EAECEAAAMCB@BBLABC@C@@EA@@DG@@HE@@FG@BLECEA@BBBABADE@@CIA@EF@@KCAACA@@AD@D@@CB@@BH@@AFAN@@CHCF@@DFABWBCD@B@NKBE@GH@B@@EJ@H@B@H@@BF@BBFBL@FAH@BBF@@ARBFCBFJHF@FAJCBCBB@BHB@AJ@BCJ@FBDD@BF@BAF@AMH@D@BAF@GQCOAE@AL@BFDHDDJD@BB@BKDAH@R@BKE@@EA@@EF@AFJ@AFFA@H@H@F@FAF@DN@BcBCL@@HD@@ADA@CGE@ADA@CD@@CV@@FJ@BED@@AJ@LC@F@@DBFAHABE@CD@@EL@FCDBDBP@DDNBBEH@HCJDHBBCBAF@@EDCF@B@NB@B@BBBDEDCB@F@DEBFD@B@AHJBH@@CF@BA@CB@@CD@@BFBJ@BAD@@FHBBCH@@DPDF@BFDBD@BEN@@BDFB@D@FHF@DD@FB@@EDCH@BAHA@AA@ACDABBH@@CFB@CFAJ@BBRADB@HLB@CTCJ@@ELAAAHAP@D@"]],"encodeOffsets":[[[122302,37607]]]}}]}