{"type":"FeatureCollection","features":[{"type":"Feature","properties":{"adcode":410402,"name":"新华区","center":[113.299061,33.737579],"centroid":[113.182062,33.765509],"childrenNum":0,"level":"district","acroutes":[100000,410000,410400],"parent":{"adcode":410400}},"geometry":{"type":"MultiPolygon","coordinates":[["@@BV@HBD@DBFBBBB@BBDABA@Q@E@A@ABADADGDAD@B@DAFEL@FAD@HKDUFQFYLABAB@BA@AAC@@@AB@BA@A@A@@B@BD@@@@@CBE@GFA@A@A@C@EB@@@D@@G@@@A@A@@B@BA@@AA@C@@@AB@@@@@@E@@@@@A@E@@A@@CC@@A@YLMDCAIEIAKAWBOCOKA@GDELGRMJIFKDK@@AAAB@@CB@@E@AAE@@BAB@CA@AAAAA@AA@AC@@I@I@@AA@A@@A@@C@@@@@A@@BA@@@A@@@AAAA@A@AA@@CA@@CA@A@ACKKAKBKFAFC@Q@KFSFOXWZWLCVBNCFEHI@ED@D@HBFBB@@@@@D@B@D@B@B@BAD@DB@@@@@@AB@@B@B@@@AB@@A@@B@@BAB@@BA@A@@BB@BA@B@@@B@B@@BB@@BA@@@A@A@A@C@@D@D@D@B@FAB@@@D@F@DAJAF@DAF@HADAD@B@B@BAD@DAD@B@@AB@B@F@B@B@DAB@D@D@B@BABA@AB@B@B@D@D@FBD@DBD@DDJTDDGF@DABDBCB@AB@AAABAAAB@C@G@@EDC@@HBHD@@BCDBJSPFDBBB@FCDF@B@@RELEFICAD@@AJCDADA@A@ALCBDBBFCBBHCR@`A"]],"encodeOffsets":[[[116028,34539]]]}}]}