{"type":"FeatureCollection","features":[{"type":"Feature","properties":{"adcode":411526,"name":"潢川县","center":[115.050123,32.134024],"centroid":[115.157677,32.127372],"childrenNum":0,"level":"district","acroutes":[100000,410000,411500],"parent":{"adcode":411500}},"geometry":{"type":"MultiPolygon","coordinates":[["@@]FIDMFKDEBK@CAEEA@AFABCBC@@ACC@CA@EDAD@BDH@DCFGHCDADCH@JBDDFBH@BCH@FBHPPBD@DADEFADBHBB@DELCBKDGDCDEFCJGTABABC@IGICI@]FQ@GAECACCC@G@CBEDE@GAAA@I@ABIHEDGDG@C@CAOKC@EBABADBLABMRCFABEBE@ICMEC@C@CDIJCBE@cACBABABEHILGDC@I@C@EC@A@EDI@C@AKWCGAAEASCCACACE@C@CFQ@CAIAGCEIKMOCAEAC@G@eFKBE@CCKKAATIDABC@C@CACECQGWICCMWGKMMGCCAC@C@EBMFABCACACIEMCECAECEG@CBE@CC@KCOACAAABEAAGAA@GDE@CAEMAAABBDABE@IIIC@ABC@CCEBCD@F@D@@AEE@ADA@AEE@CBG@AECGE@@DEACKGCC@A@CFEAEBABAPEDCLQDIDIHIFCBC@CDGHGHEBADB@@BGDADABC@AAC@CDCBE@AHCDABCFA@ABCH@D@BCD@B@@DD@F@F@B@FAF@FFD@FAFDD@JAHBD@@AAK@AIECACEAGACBEHGBC@I@CACCAGCCAC@M@IA@@@CFCDCBABCACACEAEACC@EBCDCFCD@HAFAFBFAHC@ACECC@E@EAECCACAMCE@EDEBCBOBAHGDGDCLCFEDEHGLGNIFAHBDABAFGFAD@F@H@DBBBFDFLD@FABADCDKHCHKBALEDCBEFKBCFEPKBA@CBE@EBAFEBADAF@LBV@LADD@BCF@DBDLVFJDDLHLJHDBBD@DABA@G@G@AFCF@DBF@J@F@LHPDF@FADAD@DHDBDA@CGMAE@ADAHAB@FBFBD@DABABCACA@CB@DE@AAAE@CBCBCHEBANAB@JBBBBDENAF@JBBFDHB@BABCFAD@DFBNS@@H@HDBBFHFFLJJJB@D@FCB@D@DFBH@D@BGDEDGH@D@DFDDDBLBBFDBBCP@FBFDF@BADBJAF@BBFAR@DHHFDBBBBDDBBAFBFCD@BDFAJBD@DADBDHLDHDDD@DCFAF@D@FDJBB@@D@BFDDDBFBBD@FAFCF@D@HBDAFAD@DBBBBF@BDBD@AH@H@DDFBDBD@HEH@B@HEDABBDEFADBDIJADCFBDDABBBF@B@HCDADBDABCLADCBC@CDAB@BBF@DABEB@F@DBDDHFB@BADEB@BBDFBBD@FAB@BHDDHDBH@D@DF@F@DCH@B@DDL@BCBAB@BDBBBAFABEF@B@FBD@BEB@BDD@B@D@DB@HF@BBJGD@BLBDBDBBF@BCF@BDBCB"]],"encodeOffsets":[[[118146,33021]]]}}]}