{"type":"FeatureCollection","features":[{"type":"Feature","properties":{"adcode":420104,"name":"硚口区","center":[114.264568,30.57061],"centroid":[114.212905,30.597798],"childrenNum":0,"level":"district","acroutes":[100000,420000,420100],"parent":{"adcode":420100}},"geometry":{"type":"MultiPolygon","coordinates":[["@@D@B@D@D@@CBC@CAK@C@CBABAD@DAHCFEDAF@FBJDFBD@D@DADEFCHEHCJAJ@H@D@DAFADCDAHCDAF@JAD@FANAJ@F@DBBDABABAFCH@@AB@@@BA@ADCFEAGCAFA@@B@@@B@BA@ABA@@@ABEDA@ABA@A@@@AAA@ECA@AAE@E@@@C@C@@@CD@@ABA@@BA@@@B@@B@B@B@@@BCDAB@@ED@@@@ABA@@@@@@@@B@@@@BB@BBBB@@BBBB@@B@@B@B@B@@@@@B@@@BA@@B@@BB@DBENC@AAA@@AA@C@A@A@@B@@@BCDAB@B@B@@AF@D@@@BB@@B@@BB@@BBB@@@@@G@S@A@C@C@A@A@@@AAC@A@@@C@E@E@C@E@A@@@A@@BA@@@AB@@@B@B@BA@MDC@C@C@@ACAAAC@GBEBE@CAAA@AAA@@@A@AA@A@@@@C@@@AD@@A@A@AB@BAB@@@BADABCDCBA@@@A@AB@@A@ABABADA"]],"encodeOffsets":[[[116911,31339]]]}}]}