{"type":"FeatureCollection","features":[{"type":"Feature","properties":{"adcode":420302,"name":"茅箭区","center":[110.78621,32.644463],"centroid":[110.787323,32.518423],"childrenNum":0,"level":"district","acroutes":[100000,420000,420300],"parent":{"adcode":420300}},"geometry":{"type":"MultiPolygon","coordinates":[["@@@@@AACCACCACAEBCBCFAHCDCDEBEBEDCHBB@F@BABC@EACCCCE@ABAFAFAF@HAH@BBFBDFFBDDFDD@DCFCFBF@B@FB@B@DFDJLDFDANCNIFCBA@ABCBAB@B@F@D@BAJODEFEBGDKBGDIBGBGBEDCBAD@D@JBFBJFDDFDBHDDDFDDBBF@DBDBBDDBBDDBDBBL@DBBB@BCD@H@D@DAD@D@F@HAFADAFKD@H@D@F@D@FCBEDCFADGFAF@D@DBBDDFBBDDDBH@F@FBDBBBBFBBDBDBB@B@DFDFBBBBB@HBD@BBBD@D@FBF@BFBHDHDHBFDJDFDDFHDFDBFDLDLBFDLBDDDDFBF@D@B@D@B@BDHB@F@D@BDBDBDBD@FAJ@F@DCD@F@D@BADCDEBAFAB@FAFCD@@BBDABBBBB@B@DCFBHLABAD@BDB@B@B@BB@D@D@B@@DBBAF@DAD@FBDADABED@@@DHFBBHAFCB@BBAF@B@@DBBD@BABCBC@CAOFCBEBCBC@CBABAD@@BBBBDB@ABADB@@@FA@A@IAC@IBEFEDEBCHAD@@A@AAC@ABB@ABGDCDGIGBEBCB@BBDAHAHCFCDGDCHCFILCDAE@CAECEAC@ICACA@ABC@AA@C@A@@A@A@AA@CACACA@@BC@@AA@CAAA@A@EDA@@ABA@A@A@A@@A@ABABA@AA@AAEAAA@A@A@IBC@@@@BAF@@ABC@@@ADABCBABA@BF@D@D@BA@C@A@@BAFADGFC@A@@B@B@B@BDDCBAB@@EAA@@AC@A@@BABCA@@A@KB@AAADA@@@AAA@AAAC@A@AA@A@@@@AA@C@@BCD@@AAAC@@@@AAA@A@I@A@CAAC@CCACA@@ECIAA@A@A@AAAACCA@@@G@@BA@AAE@@LDDB@A@AACCE@AA@K@CBA@CACEAAEACA@ACCACAGCEEEECIACBA@AA@GAAG@CBIAAA@A@C@CCEECE@C@AAAEAAGAI@EACCA@I@GCKAACCK@CAC@AAEEAIEA@A@GFEBIBA@EACBA@CAGEAKECE@IAEC@GCM@EAI@GCCOEKAACAEAA@@"],["@@BBBDBBADCBAB@B@B@DCB@BABABAACC@@ECAAB@BC@@@GBA@A@A@AAA@@@ADCF@@@DDBB@@B@B@@B"]],"encodeOffsets":[[[113249,33260]],[[113440,33454]]]}}]}