{"type":"FeatureCollection","features":[{"type":"Feature","properties":{"adcode":431222,"name":"沅陵县","center":[110.399161,28.455554],"centroid":[110.595225,28.570921],"childrenNum":0,"level":"district","acroutes":[100000,430000,431200],"parent":{"adcode":431200}},"geometry":{"type":"MultiPolygon","coordinates":[["@@K@IAAQ@IDGVQEGGAGOG@CLC@EG@EICUDSHO@I@QEMEAIFMHMHKDW@IEIKEMCKFOHWNIDIBEE@gEYMSKGMGKAMBIFWRMNIDI@MQECECOBKFGJMFCABK@KAIEAGAK@IFED@LGNGJKNYTOJKLMNEFKBOAQDIDELIJMZKPG@KEICQKOOHOPUBGAGCCKEMCIEWMAG@CHMHKTWFGDMBQEMIGKGMXKLUNKJQLGDIAEEAGEE@CLGBECEM@ECCGCEG@[F@JCDM@QBCBORIBMGWCKGEIAKBGAEHKDIAEWGKMGCAAMAKQ]aCWEODgCWMOECYEM@ODIFKHGBECEK@IFUEYGGASECAMCODWEWAKC@ODEAKYCAKAAIBE@IGAGDILCBKAIOAKIYBCRERIACKC@CFWHIAKFGHO@CEKSIWDADCJCFCBIAIBKAA@EPQFC@EAISCU@MD]@OEAQAECCEBGAKCDIHKFCHADEKKIAUGCCCMEAQD@DDJAHKFM@KBEAAMCEHCNOBIGU@CBSHKHGLERUNQFADBDLHFJCJGHGJGTCBADGNQJAF@LBD@FGBIFC@EACQOCAQAGAEECWCEEE@M@MFIJO@GGAI@CC@CDILMBCCABEFGTILCH@BEDKHAH@HELBRGHEDEEELSBIJAFFJFJAJEHACEMIAGTJNDPBF@DEPGLEFKDANEDI@GCUAMBKDEHCDH@L@NDFBFHF\\QTGDC@GCKDELGHGBKECICWAAI@KDSNMTCAGDCHAZBJDHDHCNMHEV@bOH@HDBDLLDDHBFEJAHB\\FXDT@FHJJJLLL^XJDHHDHHLJLPXFFFFNDJATDNLLHNLNJVJjZLHNTZRFNAHEDGBG@IL@JBF@HDFBLFHB\\DFJLFBL@JCHBPDDBTED@LFHBFJFFLDHJ@HHLFDNHDFBHLHNBHDZJXHdR\\RJJDH@NBFDHFDPFP@D@HLBF@LBJFFLDDHRLJFDF@JBHXJJFNPJLJFBB@HDLFDHAFCHEJAFFFHFFNJHLBLDJHFL@L@@FVLBDDHFHHNFDHHHDNEH@HBD@LEHADE@CPDLEJBPIH@H@FHBHMRGLGFKRGBAHBDNHFJ@FSPABBHDDCF@DDLGBGA@EDCAEC@GFA@EGBGAAGFAICAEFC@EGKAGJ@JEBGAAADO@ECCECIFOBQ@KCIKWMIGKAAF@NITAHDTAFEJIDAFAHDDNDD@PCD@JFD@RCN@RCJBFP@F@JBFVHFDDFHFXDL@LAP@JBNHNHBDGF@HEHGDMPCFDJFDZJFARGL@HHVJ@L@FJH@JBJHHEH@FXTEHGHARKHCHAFDFDFADQFKHOP@NDHADMHCNMNIBUBICEAMLCL@DAFGHKJGBGDAHGHCJEHE@FJAFIJIPERED[JQ@KFAHJNCHIJ@HGJCHFJHJ@DALAHHFNDDFHJFHJ@H@HLAFBFEAGFC@@EIDKCEBHBDHI@ADCFKAGBEEADDHJBEFCBMLMBQLE@KHCHGFBL"]],"encodeOffsets":[[[113577,29733]]]}}]}