{"type":"FeatureCollection","features":[{"type":"Feature","properties":{"adcode":441324,"name":"龙门县","center":[114.259986,23.723894],"centroid":[114.131828,23.661409],"childrenNum":0,"level":"district","acroutes":[100000,440000,441300],"parent":{"adcode":441300}},"geometry":{"type":"MultiPolygon","coordinates":[["@@MDGFEDILCAIEEEK@KCE@GAED@DADEBCDEBED@FC@GAECBAAACBI@IB@DABC@CJG@IGK@KBKF@HHFDHJRHBFHCBEACDHHD@BBFADDDBJBLH@HJDGBAHCBEAGBACAEEEG@EEGCEBKMG@GCOBKDEFA@ECG@IEGHG@C@GJCDBJQFG@IE@ACCG@COGKGCMAADEDKACDE@DCEEC@ICC@EBAADEGCICICIBI@CCEEE@CHMAIAANC@M@EBGFCBAACCGKBEEGACCECGECBEEG@@ACAB@I@CDA@CDCD@BCAA@CB@@C@C@AAECC@CBCHADE@CBCBCAEDCBAAABAFGB@FEACC@@AAGC@@E@A@G@EGAECICCECEAKDIJAJGGEKCAEBCRKPADEHOCBUCEAGACCEE@EIEECCIAEC@CHCD@DAFGAGBBNJDBFBFCBEAECAEGGCAEGCACAGAIACBEAGAEC@A@C@MAGAAAGE@GBICEEECEBGFIBC@C@ACA@@ECAEBAAIAECG@AAGMEIEAK@E@CG@GAOGEEKGEIEGAEAO@IC[AAAGGRI@EQDACAE@GCIKAQBM@@CBA@CDCB@JABCCCAGCCKACC@CCG@ADABEBAD@DBD@L@F@BC@AACDCBAF@JBFARID@FCBA@CBEAECEAIBABCFABCAAAAGCCECIAA@E@ABAHADAFCDG@C@CDABC@E@CDE@CBCBCFEJAJAFABABABCAC@C@CBCFGJABCBCFAHCDGBEDAHAF@J@FEDGDCF@N@LABAEKEEAACAC@EDCB@CDEDCHAD@HBFBJAF@LDF@FCD@F@DBDALKCAKKGAK@E@KDAAAAAKBGBC@ECMBEBAHGDCBCD@F@D@D@JCJBJFD@BC@EACCEACBCDEEG@C@CFERKDADCBGAECCCAEAIEKGACBEHIBGDEBEBIDELGDCBCJADAFAH@JALCBCDAFCFAFBHBBDBBEH@HBL@DFFHJBFADAF@HBJADEBABDD@BDFFBBD@LBHBDDDDDFFHBHBHBL@BAD@D@DDBHBFBFFHDBFBD@PIFCD@PNJHRDF@FHBBHAFBDAH@DAD@BDAB@FD@@DHLFDJEDAHBDFFF@JD@NNB@D@DENFDDHDHDDDJ@PKBAH@BABC@CDCPADEFC@KAGBALBB@JBDDDH@N@FPHDFDAFFFFHBBLFLFFDLAFHLJFH@BDDDBFNB@HBBHF@R@BDFFHDNFFHFJAAFDFBBBFCB@HDBANFFNAFDFB@HDD@JFLFHFBBBBLNBFAHDBFAFCA@DBFDHDA@EHA@EJ@BFF@FDDDGPCVADAHEHFFBFE@I@EDICEAE@AD@DEDE@CD@LBDLLDFDBFBP@BHVABEBBBJBBHBDAJFDHDD@BAF@BFFD@DFADEDA@ABCCGCI@KHBDCLADAFQ^K@@DGFGMCCEIAKC@CFGBCDAFA@CDDDFF@HADCBI@KBIF@HDHABEJ@BAJBNHDHHBFBD@FIJCBAJDDCHE@KBAF@DADGND@@HCLHP@N@F@FFDDBDD@FHFFFJBDBDAFDBDC@C@EFCDCD@BBD@F@BFF"]],"encodeOffsets":[[[117095,24462]]]}}]}