{"type":"FeatureCollection","features":[{"type":"Feature","properties":{"adcode":500235,"name":"云阳县","center":[108.697698,30.930529],"centroid":[108.856912,31.036349],"childrenNum":0,"level":"district","acroutes":[100000,500000],"parent":{"adcode":500000}},"geometry":{"type":"MultiPolygon","coordinates":[["@@TPPHXLJFNNb`JFLDFAFGDCDBPNHDHIFAFBHDBLDBFHFDIHCFBHNVBDCJIHBDLHBFCLGDADBHFFHFJHAHGBEAEB@JADLHHBD@JFLDBDDAFBFHGJBNHB@HHDBD@DFF@JEFAJKHBHCDDLGF@DDFAFEB@JAFBFDD@DJ@ADED@DFD@FADIDADFFDHDBDH@BGB@FHD@LDLFDHFNDTBF@DC@MBAFALB`BXDZFFD@DIVBBHBBCTAFABBE`EJ@FFFHDHBJEFBANAHADGDGHAJ@NDHJB^C\\CNAPEBIJGNEDAFLBHB`@TCPADIDADJXBDJDDDDPDFFDNNHPJLFJDHCFI@GNAJEFK@C@GPICCEGAUBGBCFCNGLI@EDK@QCGDGCMAKIEEICSAI@MHQ@SFK@CD@DF\\BTELFHFJBFALDLAHG@QDGDGFGDG@O@OBCHDLC^ADGHCFCZBLBFD@LELCHCJBBDFPHDH@LAH@BDAhGJARELGHELIJCLDFI^CFEFMHKDI@CD@DGFG@CDJLDFBPDDHDBJHHDDBNGJANBLFJBF@FE@AD@PKBOBQBKJEBG@KDKBOBGBQLKAGEECCBCD@DI@OCE@EAKDEBCHEDIGEAE@IBE@AEOAEBCFE@MEEAGK@ICANEBCBECKAEFU@GACICCACD[DIHSBODI@I@ED@LEBOBCFDPCHDBNDDDCFGBIL@DIFQDSJEF@FDFLHFHHH@D@FCDGAGDOJG@IFIDSFQBEOCEOGKGCK@MECIA@CJMACEEE@[FGBIAQGGEEG@EDEL@FCNABACAACEBEKIE@CBGHOAEECSCGAG@U@IAKBEAWAICEI@EDODCVUPU@IEGGA]G@EDCFCBC@MAEIAKOA@ODECAIYYGEEAEIG]@OAEEGDK@ICIECOGDGHD@EFCJ@NCDEDK@EQEEKKGOGICGAGGAKDGCUCEICI@CACILOLOC@EBOFKDE@CGDIDC@CQBE@MEI@IEBGGCKCI@IEICAEBECCMCCCFKAIBG@EGQCGCCKA]ME@M@GBKAOIKCEGAGX@NBJFD@HEHAFBFCDECKAKDC@UDCHAFHFBL@XFFDD@DELADBLF@FEJ@DDFFFJ@LCJBRHJBFABEKEAGBGCGKAECBCHIBGNKD@BC@GHOJI@ECEJUDOJET@RBTFJDLJZ^DBPGBCAKJEHEBEGECEFGEEBWCKFUBCD@LFFHAFFFFBTBDBDGJSAGBCFAFEHMBMDCHAFELCDGCKLKHEHI@EACDKJ@VFBHF@@GV@FALKBGCKFUBAJEBCKEAGDODCBIDKBIBGLKF@FDH@DADE@CCEGCAEFGDAAECEAGFANBbBFCCEDECCSOACBICGDEJ@RHNDbJF@FCJYHANDTDBDF@BFNA@DLDBAJDBBHB@DLB@EBKHDDEF@FCHO@MBIDCAKAA@GBIEE@EE@CCDGG@GC@CKCAGC@EC@IIABEEGJCDCd]NENKDC"]],"encodeOffsets":[[[111524,31316]]]}}]}