{"type":"FeatureCollection","features":[{"type":"Feature","properties":{"adcode":510302,"name":"自流井区","center":[104.778188,29.343231],"centroid":[104.702347,29.272914],"childrenNum":0,"level":"district","acroutes":[100000,510000,510300],"parent":{"adcode":510300}},"geometry":{"type":"MultiPolygon","coordinates":[["@@@@BABE@@EAA@@@C@A@EBA@A@AA@CACCE@A@E@AAC@@CACA@@AC@AA@A@@AAG@@@A@@BCBABABC@@@EAC@A@ABAFCFGB@B@HAB@B@B@H@D@D@DADCBCDCDAZCL@HBXLJBDAB@BCDDB@@BABA@@@BB@@@@AB@BAB@@@BB@@B@BB@@A@BBBA@@B@@@@BB@@B@BB@@@ABB@@@@B@@@B@@@@B@@B@@@B@@@B@BBBAB@@@@@B@@@B@@A@@BA@@BA@BB@@@B@@@B@@@B@@B@@B@@@BA@@@@BA@@B@@ABB@@@@BB@@A@@@@B@BB@@@BB@@@B@@@@B@BA@@@@@B@@A@@B@@@B@@BAB@@B@@B@@A@@BB@@@@AB@B@BC@@B@@A@A@@B@B@@A@@BA@AB@B@@@@@D@BBB@@BBB@@@BBB@@@@@BB@B@@@@@B@@BB@@BB@@@@A@@BBB@@B@@@BA@A@@B@B@@BB@@A@@@A@@@ABA@@@A@BB@AB@@@BB@@@@AB@B@DA@@@@@@@BA@@@@B@@@@AB@@@@@B@B@@A@@BABB@ABB@@@@@B@@@ABA@@@A@@@BB@B@@D@B@B@@@@AB@@@@AB@@A@@BABAB@@@B@@@B@@@@B@B@@A@ABB@@B@B@@@BB@BBBBA@@@@@@AA@@@@B@B@@@@BBB@B@@@@BA@AAA@@BABC@@@@@@B@BB@@@BABA@B@@@@@BB@@@B@@@BBB@@BA@@@BB@BA@@@@BB@AB@@A@@@A@@@AAA@@@AB@B@@BB@@BA@@@B@@@B@@@@AB@@@@@B@@B@B@@@@@@BA@@@@@DB@@B@B@BA@@@@B@@@@B@@B@B@@B@@@@@BBA@@@A@@D@@@A@BB@@@@BB@@@AB@@@BB@@@B@@@B@@@@@BB@@@BB@@A@@@@B@@B@@AB@BB@@BA@@@@B@BBBB@B@@A@@B@@@BB@BAB@@@ABAB@B@B@BB@@AB@@B@@@@B@@@@AB@BA@@@B@B@@@B@@@AB@@@@B@@@@@BBA@B@@@@B@@@B@D@@@@@@@AB@@@B@@B@@AB@@@B@@@@B@@@@@B@@B@B@B@@@B@@@@B@BAD@@A@@B@@@@BBBB@@@@B@@@B@@@B@@BB@B@@B@@B@@A@@BB@@B@@B@@B@BDBB@@@@@AB@@@@BB@@@@B@@A@@@@B@B@@A@@@AB@BA@@@@B@@AD@@AB@B@@@@C@A@@@AAA@@@@AA@@@@@@BA@BD@FCB@@@@@@@B@@A@BBB@FJBBA@@B@BB@B@H@B@@BADA@@B@DABB@@B@@@B@@AB@BA@@@@D@@B@B@@ABCBAB@@BBBBBAB@@CBA@@@AD@@CHC@@@AB@@B@D@@B@@B@L@B@B@@ABA@ABABCBA@@BEB@D@B@@DDFB@B@BADB@@@@@@@B@@AB@@C@C@@@B@AF@@A@AB@A@A@@AA@@ABEFAB@@AB@B@@A@@A@C@@@A@BA@@@A@A@@@A@@@AA@@@@A@B@@DA@@@IC@@@@A@BBA@A@A@@@B@@BB@@@@BB@BB@@@@AF@@G@CB@@@B@B@BABA@A@AAA@@@AB@BA@A@A@A@@BEA@@A@B@DDAB@@A@A@@B@@BBBDA@@BA@@@A@@@@A@@AA@@ABA@C@A@A@@@ABAAAAAAA@C@@@@@@A@A@ADABAB@BA@@@B@B@BABB@BBB@B@BA@@D@B@@A@A@@@A@AA@C@@C@@@A@@@@@AAB@B@@AB@@@A@@@A@A@AAA@@AA@@@A@B@@@BAB@@A@@@A@@@@C@AAB@@A@A@A@ABAB@BAA@ADCAA@@A@C@A@A@@ABABABA@ABCDA@AD@@@BA@C@A@A@@A@@@@A@@AAA@@AB@@@BA@@@A@@B@@@B@@@BB@@@@B@@BBA@@BAB@@@@AA@@AA@@@AA@A@@@A@@@AEGAABCDA@@@AAAAAE@C@EBAB@BABABABCBE@@@CB@@@BA@@DAB@@C@AB@@A@AAAA@CDG@A@A@C@A@ABC@AA@A@CB@BAD@BA@ABA@CECAAAACAACACAAEGQGK@AAAAA@AACA@@@CB@@@BAB@@@B@@@B@B@@A@@@@BB@B@@@AB@BA@@@A@BB@@@@@BAB@@B@BB@@A@AB@B@@@@BA@@B@@@B@@@BBAB@B@@@@@BA@@B@@B@@@@B@BA@@@A@@B@@@BAB@AA@@@AB@@@BAAA@@BA@@AA@@@@BBB@@AB@@@@@@B@B@@@AB@@A@@@@BBB@B@@CB@@BBB@AB@@@@@BA@@B@@A@@@A@@@CDA@A@@A@@AC@AACAAACCA@@A@@@@B@@@BBB@@@BC@@@A@CAA@A@@B@@@@@B@@BBA@@BA@ADA@@BA@A@@@AA@@@A@A@CAE@A@@DCDA@@@@AAA@CACCCAA@A@@@@B@@@@@BBB@@@BA@@@A@C@AAA@AAAAC@AAAAAAAADADABA@AAC@A@ADC@A@C@@@AB@@ABAAC@@C@@A@ABA@ABA@C@C@CA@@ACBABA@A@A@@BABA@AAAA@C@E@@A@@AAA@@@AB@BAB@@@@A@@A@CBAAAABCBA@CAA@@@A@@D@@BB@@@BAA@@@B@@@A@AC"],["@@BE@@B@A@@@AA@@BAA@@@@@A@@@@A@@B@@@@@@@@AJD@@@@@B@B@@AB@BBBLFBBA@A@A@A@MGA@"],["@@BE@@B@D@@@BB@BADABA@@AAA@@A@"],["@@AB@B@@A@@@AACA@ABADAB@@@B@@B@B@B"],["@@A@@BCC@@FB"],["@@@@@@A@@A@@D@@@AB"],["@@@@A@@@C@DCBD@@@@@@"],["@@@@@@@BA@@AB@@@"],["@@@@@@@BAA@@@AB@@B"],["@@@@AAA@BA@@B@@D"],["@@B@@BAA@@@@@@"],["@@A@@B@C@@BB"],["@@@@@@@@@@@@"],["@@@@@BAA@@B@"],["@@C@@@@AD@@B"],["@@A@@@@A@@BB"]],"encodeOffsets":[[[107148,29959]],[[107301,30061]],[[107322,30053]],[[107344,30056]],[[107285,30068]],[[107261,30047]],[[107149,29961]],[[107259,30049]],[[107260,30048]],[[107275,30066]],[[107265,30061]],[[107308,30055]],[[107272,30067]],[[107266,30060]],[[107302,30052]],[[107272,30060]]]}}]}