{"type":"FeatureCollection","features":[{"type":"Feature","properties":{"adcode":510521,"name":"泸县","center":[105.376335,29.151288],"centroid":[105.498675,29.11915],"childrenNum":0,"level":"district","acroutes":[100000,510000,510500],"parent":{"adcode":510500}},"geometry":{"type":"MultiPolygon","coordinates":[["@@@@AAAAC@A@MHGFCD@B@BB@B@@@CD@@CAIICCEAE@AACAAAC@C@CBC@AAWSACECCCECAACEGIACAC@CGKACACACAECCACCEAACCGEACAAAE@CBC@CAIBE@A@E@EACACCCC@E@E@EBA@C@C@AA@EAAACAAI@C@A@AA@CBC@CDARCB@BABC@AC@AA@A@CB@B@D@@@BC@A@CCAECACCAGICAIGAAGGEEAA@CBCBGBCBABEBA@AEGACECCAAAACGICGCECCCAIGCCCCECAAACACACACAAACCCMAGCAECECCA@AAAA@C@IBCBG@CAACAACAA@CBC@ABG@CBAF@F@DAB@BCBCBCBAFAD@D@D@FCB@BBBD@DDD@BHBFABCBADBBDBBDDBBHAHCF@HAD@DA@AAAECAA@CDCJ@H@D@DAD@BBBDB@B@@ABC@EEIAC@CB@BAF@@A@EACAEBA@ABCAGACAAAACCCAGCCAAAE@AAACAAOICE@C@CBCBCFCDAFAJ@B@BCDCBAD@FAB@BBDD@BBB@DABCDEDABCJBDBFDDDBB@B@NDDBB@DABABABA@CAC@GBABCDCDEFEBABCBC@G@CCECAGAG@AAAC@E@EDCBCBAD@B@DBNLFBF@DCDEDCDAD@JAR@H@D@DBBD@DBH@HBBDDCDABABADAB@BC@@B@B@DB@DB@D@DCDCBAD@D@H@JFJBHFHBF@D@B@DBDDDBB@B@BAD@DBD@B@BFJBBFLDFDFFFAB@@E@A@ABABCFADCH@D@BLDD@JEB@FBD@D@DA@BDFBBDBAB@@AB@BBBF@D@ABABBBBBD@D@@A@A@@B@DDBBFB@@ABA@@@C@@BDBA@C@AB@B@FBB@B@D@DAFBBB@D@FEBAFAJ@FCFCBB@@DA@@BA@ABADBD@BA@CDBB@DABAB@AAFCH@FBFBJHDDH@HAHBDDBFFHFABADSFCDA@A@C@CBCBAB@@C@AACAABG@ABAB@B@@C@ACG@A@CDCH@H@H@LHHHBFDDDD@H@FHHHFD@D@@CACAABABCD@DAFADKDABCD@FDHFD@BA@CACCCCCAC@AAAA@ABABA@A@AAAQBEDAD@F@DBBBD@BAFEDAFABCD@DC@A@A@AB@D@D@BBFCB@DAD@BC@A@@CA@ADAFKBE@AAAECEAAC@ECGKEAE@M@G@GBEBCDAFCNPRJ@@DBFBLBHBD@DALCNEHEHGDONOTK`ELGFEFBB@BBD@D@F@FADAD@D@FA@A@A@ABA@@D@BBHFDBB@BABCBAB@DDFBB@B@@EBAB@@BB@BHBBBBBDDB@B@BADAB@BBBBFBB@BCH@BBB@B@BB@DCJGBAD@D@B@BB@BAB@BAD@BBBFDBDADB@BBJ@B@BB@@BBABA@@B@B@D@BDDDB@D@D@B@DBBDBDD@B@BAD@BFF@BDBBBAB@FBBBB@BBFB@B@B@@BBF@B@@@BBBAD@DBBDDDB@DB@DB@DBDB@BBBFD@D@@BBBA@@@@DB@EDABC@ADA@@@@DABAB@@ADA@A@@BBB@B@B@@C@A@A@ABB@BB@BA@@@BB@BA@A@A@AB@@AAABB@@B@BBDB@D@@@@BABA@@BBBBBD@BDBB@@B@BBCB@BBDBBBBBF@B@@@BBBBBBB@@@FAFA@IBEBEDAFAFAHAFADEFGFEFAF@H@DDHBLFJJDPFJD@HCFEBEBCAKKG@CBCD@H@DDLABA@A@@B@BBD@B@BAB@BB@@BCFCFEJAFADABABA@CB@AC@C@E@EBABAD@B@DB@BFB@@B@L@H@F@DCD@DBDDFDHFPABA@A@A@CBAD@BBDBJBNKVGRIVAJALBJDHJBPBRBBDCFIDKDGAICKIGEEGACAEBAACBA@@@AEAA@C@G@A@CBEBABCC@A@EBCFEFEBCAGGIIAG@C@@BG@GBGDEFCFJT@FGFCDEBGBEEQKACAGCECIACEAC@@FBNBJ@FCBCBKAA@ABA@A@GCICGAC@C@@BA@A@EDEDA@A@A@C@EBGBCDA@ACACB@@AAACAA@A@GBCBE@EAC@ECA@EAC@KICAE@CBGDEH@D@DHLBBAB@BCBCBC@A@CAYKEAE@EBI@C@ABBB@BADEBEDCBC@I@ABA@BDB@FBDBFD@B@B@@ABA@@B@D@BAD@B@BB@DBH@BBBB@B@B@BA@A@C@C@A@A@@D@@BF@D@B@BADABEDCDEDE@AA@C@EAC@AAAAAA@C@CBABC@E@E@KCEACCCCACCA@@AD@DC@AAC@@@A@C@@@CAAB@AAAA@A@ACAAA@@BQADAHC@C@A@AAACAK@C@CAAABABADCFABA@A@A@AAAC@A@AAECA@CA@@AC"],["@@@@AB@BA@@ABAB@"],["@@BDB@A@AAA@BA"],["@@@@AB@A@@B@"],["@@BBA@@A"],["@@DBC@AA@CBD@@"]],"encodeOffsets":[[[107913,29985]],[[107918,29991]],[[107916,29988]],[[107894,29997]],[[107898,29990]],[[107914,29987]]]}}]}