{"type":"FeatureCollection","features":[{"type":"Feature","properties":{"adcode":510726,"name":"北川羌族自治县","center":[104.468069,31.615863],"centroid":[104.264989,31.936796],"childrenNum":0,"level":"district","acroutes":[100000,510000,510700],"parent":{"adcode":510700}},"geometry":{"type":"MultiPolygon","coordinates":[["@@lJFBZLJBFDABCHGFCBC@MHCDADBD@DAB@FBFBTBBDBBBBDDF@BGF@BBFBFBFABA@KDEDA@E@EB@BADCHBFABIHCBKDEAIBABBFDD@BCDDJJD@B@DBDB@L@JAD@BBDBDBF@DBHDDDHDDDNHPDHBFDFFDBJBHDJHBDFHB@B@NIJEJ@HC@C@ACABCDIHGJEDABABEF@JDJBFBPLJHJLHFFFLHABGFABEJCFBFFHBF@BABGAGAE@ABCFCBIHAD@DBF@DBHBHDLHRADCB@D@BFDHLDBJDHBFDJLBHCBEHGHCFBF@DADIHCBC@IEEAGAGAMEMEA@CBGDILCDGDCBE@GBEBEDAFAD@L@FBHDJBDC@M@K@EBCBEBC@MAC@KBKBEDEBEBABIAEAA@C@GFGDOBC@G@E@CHCBEBCDIHEDEFEBE@GAEBCBMJEHA@C@ICABIFCDEDCDCFEFABMFCBCDCDADE@G@CAACACBEBIBIBG@CAAEAE@GBCAC@CEGGEIAAEIGICGCCIAEAGAGBEDCDADCFAHABIDIDGBMFCBADADAFBH@DA@GFMFIBGDCBMDGDIDKBEBGBIFABGHGFCDAF@BCHCFKLCFCHC@IAC@KBG@CAGAE@IDCBAB@DADCDCBKFMFEDAFBDDL@D@LBHBHBLBDDDFFDDBHDH@FADA@CBYBQ@K@IAQGMEKEICIEKCECGGAA@AACCEIAGCECEEACAI@E@IAIIKSEACDABEDGDCDCAEDE@CD@@EA@ABE@ABGNIDEBGDCBWAC@EAGCMEAAAMA@KDABCAOCMBGBQBG@GBEBEBG@MAWCEAIECAI@GAEAECEAE@C@EFEDGLCF@BEDGJABC@EAOAA@GDGDEDEBE@EBE@GCQCG@EBGBMHCBGDEFABC@EACAC@CBGBIBIBMBMDMBC@A@@ADG@CDIDGDIBGAIAGECA@CBGBGBG@EBKBC@EA@AAEBGAEBE@CKCGAECAE@GAE@CDEDIDKDGHKBE@AGIEIAA@C@EACE@GACAOEGC@C@C@ECCEAE@AAEC@CCIACGAACAABEBEACECEAECIGACEIBI@G@ICECG@C@G@EAG@CCCGGBCJEJGHATBJAJ@HAH@FALEHAFANBJALEDCRILKBABAHAF@J@DAFCFAP@D@F@D@FNBDDBHDFBN@HBFBTHDFFFDBBADCJMBAD@FCDGJGBAF@DAAG@EBE@CBCFAPCBC@CCGAI@G@IBABAFBF@DADCDGBMBKBEBADCJDJBNFF@NAN@HBDBD@BABA@MBCRGFAH@JBDBHBBALGBCBKBEDCDEDAHBDBFDJFDDHBF@FED@L@R@FAFEB@D@P@LCDA@CAGB@FEBABCBAHBLED@BBBBCJ@BB@D@B@FI@AD@JF@@BACKCAE@AA@IBABEB@F@@ABCA@E@CC@C@AL@FADA@CA@AA@ADAB@FBBACAAEHEBA@GAC@CDAHABAACGGAA@CDE@AAEBC@G@GBEAGAA@ED@FALCF@JBPLNBJBJD@BCJBBF@RDFFDHDBDCD@DDBDHHJ@DD@BAFB@FBDB@BBDBDHDLHF@D@F@B@HBF@LJFDHBF@B@FEBEBGDI@IDC@CAI@GDADAFEDCDCDAD@FB@@DEBAHIDGFAD@HDFBDBDABE@CCSACGGAC@CBAHALCFCHCB@LBHBD@BADC@GBCBAB@@EAEACACFELDBCBBBCAECAEDAAFCG@@CFABAEBBAHCAACBAABAAACA@ACAGBAA@CDA@@A@CAE@ABC@ACGEAAGEDABB@AACECDADBDBBAAADADA@ABCB@CC@CC@DC@BDBDA@CD@@CA@@AC@@BCA@CDAAAAAACDADCB@DC@ADABAAAB@@CCABAPLDEBAD@BAD@BEDB@@D@AABC@CB@DDBBD@AADAC@AACA@ADCCCBACABACADADAAAAGD@FAB@BADDBA@AFAB@AAABCCD@@ACC@CAAA@BBE@DCBCBAAAAABA@CBG@ABA@AAAAAD@AEDC@AA@DALBFDBDBBDBBHFDB@DBDCDDD@AE@AHCAADBDABDB@BABBD@@@B@BDB@BBBBB@DD@BC@@BD@AD@DC@@DBBA@@DA@ABABBDEBABFDH@HEH@F@NHJHPJLJJHHHFJLDD@DABD@DBBD@ABDF@@BD@@BDD@ABC@BDC@CBF@CB@@C@CBABBBA@ADAAAF@DADBBDC@@BCBBABCB@BB@BBABBBBBBD@DAD@@@F@@CF@DBBADABBBFCD@BDDJ@D@DBBFBFBF@D@JDFBFDF@LFLDNHHFNFJFLFHJLHBBBFADFDBDSJCAED@DBDeRG@ABAFH@"],["@@TILHADAFC@E@EAA@ADBBBBBBCFIFEJADBDkIFCACfQD@HGCA"]],"encodeOffsets":[[[107070,32512]],[[107095,32494]]]}}]}