{"type":"FeatureCollection","features":[{"type":"Feature","properties":{"adcode":511681,"name":"华蓥市","center":[106.777882,30.380574],"centroid":[106.752893,30.316075],"childrenNum":0,"level":"district","acroutes":[100000,510000,511600],"parent":{"adcode":511600}},"geometry":{"type":"MultiPolygon","coordinates":[["@@DABIBEBCBABCFG@A@A@@AAC@E@C@C@AACAAC@AA@CAE@AAAC@AAAC@A@A@E@AAA@@BA@AA@@@AAAA@AA@ADC@@BBBBBAAABAFBB@FB@@BAAA@C@AB@D@B@@D@BB@BA@A@@AABABAB@AA@ACA@AD@@@BCB@DBBBBABA@AC@AA@@CEEAAA@A@A@@DABAA@CAAA@@DEBCBABA@@B@B@@DBB@@B@B@BABCBEAAC@AAAAAE@ABAD@DDNFD@B@D@B@@A@AOS@A@ADAD@J@D@BADA@ABE@C@AA@GA@@AABC@@D@B@HFDBBBD@DBBABA@AAC@AACBABABCB@D@FD@BB@D@DA@ABA@AAA@@EEAA@CDCBC@CACAE@C@CBC@CAG@CAC@CB@DADBJBD@D@BBD@@A@@AC@C@ADAB@D@D@D@D@F@D@@L@FBFBDBDDBB@H@@@BBBBBR@DFDBD@@@HBBBDBBD@JBBBDBBBBDFPDDFHFLDJBDBBDBJBDBFBFDBDDFDFBBHDBBDF@LBHBFAD@BAJBDBJBFAFAL@B@D@DDDBFBDBF@FAL@DBDBDDBBBBDBB@DDHBBD@HBH@DBFDD@DBFFLNB@DBBBBDDDBHDNBFHFDFDLDHDDFDFBBBD@JFNHDDDDFJHNLVJPNTXZPVICICA@@@AB@HADABCDEDKHGDGBE@EDA@CB@B@F@BABC@GAA@A@EBEDADIDEBABA@A@E@E@@@AD@L@D@B@DABCBADGBABE@A@AAC@C@A@C@MCC@CBCAAAAAA@A@@BAB@@A@@A@A@@@AB@@AA@A@ABAB@DA@@@C@@@BBB@@BBB@@EBA@AACC@A@A@@A@G@AABACA@AAA@A@AB@AC@@A@EAA@@ABAB@@@@ACCA@AAG@E@E@CAEBGBG@E@E@A@E@ABCAA@AABCBCBA@E@@ACCAAAMEGAIAEAEAAACC@@AABABCDCNGFAJADAFABA@A@C@A@AEGGI@AEACAE@E@EBC@CBC@ECGCCCACCE@C@A@C@ABA@A@A@AGGGAE@A@C@C@ABABABBD@B@B@DADCFEFABA@C@GACCAABCLMFC@CAC@K@ECI@ECECADC@A@AB@B@DA@@FA@@BBB@B@@CDABAD@BDB@DBBAB@DCBCDA@B@@BBB@NCFABAAEAE@A@ABADAD@JCFCDADCBABC@ABE@G@G@CACAAA@KAA@AA@A@AAG@A@C@CEE@AACAAC@EAC@ABG@C@A@EAEA@@AAAEAC@ADABAB@D@DBBABABA@AAAAACCE@C@E@C@A@CAAAAAACACCCAAE@A@CBA@GBAAA@ABAFABA@A@KAC@CBADABA@I@A@"]],"encodeOffsets":[[[109193,30994]]]}}]}