{"type":"FeatureCollection","features":[{"type":"Feature","properties":{"adcode":520329,"name":"余庆县","center":[107.892566,27.221552],"centroid":[107.701578,27.389186],"childrenNum":0,"level":"district","acroutes":[100000,520000,520300],"parent":{"adcode":520300}},"geometry":{"type":"MultiPolygon","coordinates":[["@@d@XG\\EXARATIPGT@P@PBLAHE@ECCQGSCIIFMTAZAVCZ@PANBFABDBHBBF@D@BADGBGBAD@FFD@BADE@AAACAI@CCAGACEAK@CCCC@ICGB@D@D@HBFBJ@BFB@D@F@HBF@B@CG@ABCFA@CAG@AHGFAHGLAPBLBHHBHCREN@NBFBDDBH@HAHAJADBFHL@DDDFBDBBDD@D@DDDHDD@FCHCHAFBLAD@HAFBHFF@NF@FEFGJ@B@DDFD@T@RFNFDADDJDDFRBPDPJJHFLFN@NELGLKDQBKDMNCJCTCH@FE@MFIFEFKLKBCAA@ECICCAA@GF@BFDBF@FA@S@AD@BFBH@HFHP@J@FAHCBEDG@A@GAGCIEC@ECACIGKKAAHGLGBCDEBC@EACEAI@CAC@GDCDCFADCDEF@DFBBDCDCF@BCFEDCBCBEDoE[WOEWAOCS@UHGFALDPBDCDC@GAE@GDEBS@EDAF@DAD@DFBBDBJBB@FCFCBQFGDABADBFBDDBHBJBV@DAJAHADDFDETAVDTA\\MLO@S@QHOLCLDRLPRJRJF@LAVHFBJ@@Dl¨AN@FCJIFGDIBWBQ@M@IHGNCVWTcPGFBJKJ[PKHE@K@K@KHEJCLBLCNGNKHODODSF]DcRGESKWGMGMKGODQJODK@KKKOGUEOEWQIIM[EUMkEQCSCQ@MJUPELCJKRWASSkCSO@KAWM_]oIMOMO]OCCEECKCMF@JAFCFADCBANFPBRBRBP@NOF]BO@G@GD[@GEC@A@AE@AAGCGEEEGC@AGEC@@EAEBCBC@CAEACEAGCIAIKAE@KJU@MCC@E@CBCFCDAD@@DGJ@BBBBAFCB@DDD@D@BAJC@IBAHAHADAACE@@C@CHCBCDCHABCBEJIHEN@HDFDBF@POXGP@F@FFBF@JS@@LUNKJCV@FDBBJDJHIVQREPLL\\FVFZFRBLGJGLCJ@VHRJNDNCAIEQMK@KJETELA"],["@@A@AB@HCBC@EACACAEAAC@ABCBCBCH@FABABEBEB@FAFBDBJBDB@HADEBCFABIB"],["@@@BGBAADCD@BB"]],"encodeOffsets":[[[110251,27889]],[[110536,27813]],[[110507,27989]]]}}]}