{"type":"FeatureCollection","features":[{"type":"Feature","properties":{"adcode":522625,"name":"镇远县","center":[108.423656,27.050233],"centroid":[108.467787,27.115635],"childrenNum":0,"level":"district","acroutes":[100000,520000,522600],"parent":{"adcode":522600}},"geometry":{"type":"MultiPolygon","coordinates":[["@@CAMGOEUKKAEB@AK@IBKFODGAIAEAGAOGKAUCGBG@KCMEO@GBINGJK@ICCICICEGEG@CFCDIBKCKAGCIBIBEHCJ@H@JDNHJHLPLHJDHEPCDK@IAW@KBQBQ@OCKCKEMAG@GHEHAH@JADGTBJDRBD@H@FCHEFMBMDg@U@Q@UBSCOAGBEDEJCHAFCJEBGFCDAJBP@FCJILOBOAKCOCM@SFMLELIHIDMBQ@ODOFGHILMNEJIKGEIGGCCAEBE@IDK@GAGCGCWAQ@MFKFKJcRGBM@OCMGIGKSCABEGMGKImISEKEEGAC@CKEKIGKEEGAG@GHCJ@`JHHHFLJJJLHRHFCFEFGHAF@FAFIEOEICIBEN@PHHFFHFBJ@HCFCAEQeKUEMCGBEFMJOHMJK@IDOCMCOKQIUKOAIDEDCHANBTFTPJDJBLALAHGDIAGCGEKMOAIDGpuBMAsMgLS@@IACBEFCFAHAJAHAFAHGFG@C@CA@ACCAG@ICCCBADE@EDEDC@AICEE@EFGDGBIDAD@FBDBBBB@BCAGBBDCBEBIAIAGCCMCG@EAEEAG@KDKDGJGHAFBFDLHJJHFLDNDPFNFNDTDJ@J@P@N@VFJAL@TGD@DG@ALEHAD@DCFGD@H@DBB@FABA@CBMCEEKACE@E@CBC@@GGQM@CAAEGEGGC@IB@ADEBEDCB@D@DAF@B@JBD@BBD@L@H@BBBDFFHBL@F@H@NDDBDBFCFAHGDKBICIAGBIDEHAJBJBFCDGBGBEAC@GD@DAF@F@FCDEBA@AMBA@CACC@C@CF@FCDEBK@ABEBABEBC@CBEBAD@@FBDBFDHNDJBPL@@@FBDFBNBDABABALDRBAD@FBHBBFBDBFBBBABG@AHDBF@LFB@FBBDDDD@BDADEDEDCBCDGHEFBBAFAFCBEAECABADKHABAFBDDDHFJFDBDFBJDFADGHEL@J@N@DCDGFCD@@@FABCDAN@HHAJBD@D@HCBDBF@DABEFCBCDABAJAHBDBDDDDDHFFFBB@HDFDF@@AB@BCDDFD@FBHJFLHJBFNLLFDBFADCF@D@HBJNJJLLPNTRRJRFNAVBLANCJIJEHCPCRCFEHGDGBGBGHIPMPKJIJ@LDFDBHBNDPLVPRPNBFFFBDDBB@DBBD@BDDDDIDEBGDCBDDDBHDFDFFDDBDJAF@DABE@CBAHAH@B@FDHBFBDBDFDBF@JCF@DB@DABAD@DBDBBBFBDDFBBH@DBF@FCBAHGBGFBHD@BDFBB@DAF@B@HBFAFCFOLABK@CBCFABGFCBE@C@EA@@AFB@FBD@BD@F@HBF@DABIFADCBEDADAJAF"]],"encodeOffsets":[[[111457,27836]]]}}]}