{"type":"FeatureCollection","features":[{"type":"Feature","properties":{"adcode":530621,"name":"鲁甸县","center":[103.549333,27.191637],"centroid":[103.420438,27.207184],"childrenNum":0,"level":"district","acroutes":[100000,530000,530600],"parent":{"adcode":530600}},"geometry":{"type":"MultiPolygon","coordinates":[["@@@BKLAF@F@F@FBDBFFD@F@BBBFDJDBBBDBJ@@JDLBVFJBFBDB@F@D@DGHEFEDADIHAFEDEHIFA@I@WFKBCF@FAFABAD@FDHJPDLANADKLADAFGHE@A@AC@C@AI@@CGECACAWBABEFIBEBCBCHGFMHC@KIMEEGAAC@@DCDEAICGCE@IFC@AA@GAAGBEBABCDKBEBGAAAIIAAE@CAIACBEBADAD@FFJDFDLDLBF@JBDFLDFFJFFDFDJ@BDFDFHHBHAHFFDJ@FAFIPCJ@H@FJZDJDD@BAFABEFGNCDGHAFCDGLEH@D@DFJDJADCDDFBBBF@L@JCFIDCBCD@FFHBDBHDDBBBBABC@CBCFCBC@CAEECAACDA@CC@CHCDGB@BADCDEDFBF@EH@HBHFF@BGH@HDF@DEDGHCBEDABEDCCBCACACGGAI@A@I@CCECCCBABEBCD@DEBABEDKBCDEBC@A@EBAAEBGCA@CAC@ECEAE@ECCACAACAM@GFGAC@GDIDIHGF@DADADABCBCAKEGCICAMEC@EA@CDEBEDACACC@E@CFGLCBADEHED@HEBA@CCAC@OBCC@CDCHEHAHEDERQDABCAAC@UEGAGI@CFENEN@HCBAACACCCCACE@GHKDC@CMGCAADIPCDCBC@EEAKACACC@GBCF@DEBE@C@AABEAAAA@CBABC@CAEEAEAACBCHG@CCAIDEAABABAFEBCBGBGDIBCBKJEBADCJEJEFEHADCDCF@H@DCDABMBI@CDCDAJABIDABADBBJFBB@DIBEDGFADABBD@DEDGDC@C@CB@F@BGBCBEFEBADC@@GCAAEA@C@@BABA@ACAABGACEAA@ABBDBF@FEJADC@KGC@C@@DEAACEACKCAS@ACAAA@I@CBAAECA@E@C@IBC@I@FCDCHEFEBAFAF@FGF@D@HBLDHALED@DA@CBAFABADCBCBAAIBCBGDGBCHIBEDG@CAIBGAEGK@EDKAEBEFGDGDQ@CACAGBM@AAGCEDE@AAG@EMQCG@CKGC@ACGCECAA@AACGCAGBGDCDAJMDC@A@E@CFCHCDCBCBAACBEDE@CAE@EBAFADCDCBCAA@ADEDCAG@CBAFEJCDAFCBEFGBGDAHEBEDCFAHAJBF@F@L@D@HAH@FCF@BCFMBCACDEAKAEAEBGCGIKAEBGCGAAACCEEIBK@ACGKEAE@CDGBAFABC@E@CDADAHAFCDAFAF@FCJ@B@HADADCDCDABEAEDE@CJCBABCDADADBBBBD@H@BFDDFHHDDDBJDFHDFHNBLDFBDBFDDBDB@HAH@JAFABABABEACAG@E@ADCD@F@J@D@D@BAHBDADCJCHE@A@CBCDEAE@C@E@EBABCJCF@BADA@ADCFCJIHAF@F@FBBDD@HFHDFBDBHJDHDBF@J@F@D@FA@ABEDCDAFCJCHCD@D@FBD@DBFHDDF@LBJ@FBHDBBDALAFAHCBCBIDCLADALAD@H@D@FAFBD@JBH@BBFBBF@F@BAF@DBDCBBFHBLLD@F@BBCFAFCJBHAFCBCAC@CDEFA@EJCDAB@HCHGJ@DDBF@FFBFBFDLDDF@HCNIHAFCD@HANEF@B@HBHA@BBHAJCHCFAPADEBEACAIAQBEFCDIBC@@FDFBJ@FBBFJ"]],"encodeOffsets":[[[106115,27768]]]}}]}