{"type":"FeatureCollection","features":[{"type":"Feature","properties":{"adcode":530922,"name":"云县","center":[100.125637,24.439026],"centroid":[100.228076,24.320177],"childrenNum":0,"level":"district","acroutes":[100000,530000,530900],"parent":{"adcode":530900}},"geometry":{"type":"MultiPolygon","coordinates":[["@@BK@CEMIKEKAI@G@YEEGFMFO@MCKAMBQ@CAIGC@GAGCC@GBC@IAC@ECI@C@GAKCCAMGAA@ABC@EAC@C@EAAECAAAKBEDEHEFBDABAFG@EFGFABCFEDEDKDEBCCAAC@CJKHGFEHCHCJ@@@DGBCJEBAHGJEAI@AHDJ@L@J@DAHGHCD@JBBACCGAAAFEBA@CDGAACAAGC@E@CABCJKBCBADCDAJCFAN@FCBADIBCHEFGHCJELCLCLCL\\HHFDLHJJHHJFJFHHRHJDRAPAFBFH@NEJBLFDZ@HDFNLPJLJJNDP@HDBJCN@J@PCLFHPBV@NAFCJEBCH@BADBFDDBDBBBBBBB@BBDB@FF@@DDFDF@@DBD@D@BADA@ADDF@FFDAFEFCBC@@FCDBDBBDD@BABG@A@CDCFABGAEBC@AFADCBGBABIBEBCACAC@BHCF@BBD@B@FDF@B@DAD@DDB@DDB@FD@DDN@HAD@B@FCHBBBDAJHBBHDBAF@HH@DB@DBBBFBB@@DBDADAF@@@F@DADADBBB@DBAD@HBD@BDBDFDBDAH@H@JCDBDABA@C@GBCHMBAJABE@G@CDAF@JEJCJEDCBCAEBCBGBEBE@ACG@CDCF@BA@CCEAI@KBGBEDCBEJMBE@E@CACEGCGAKCECACCAC@C@EC@ACAABAFCJGFDFATIVKJGHGDEFQTOHGFGHEDABCAGBAFKBC@C@IBEBGBE@K@KBGBCFCD@FCPGDCFADCAOAEAE@QCG@C@GJMDCFAHEF@FBHPBH@LDDHFF@LILCLEJMFEDFFLBBH@LDJAN@PATETGNININEBAD@HDB@D@DBBBAF@DDFAX@HYlJZAL@HMLMR@PCRLNJLPHPFN@PIdGXHXDTFXFTDRLRNHRBJNdFPFXFXHN@\\DPDL@LCLAXENBFBVCTCPGHGFEF@DL^DXGRAFBRCJFVCTKZDPBTF\\E`FPA\\CVFRFNDNLNNJZNNL@FAHEHIFEFAFAHAF@HAJ@DADABIDE@GDGHGDOBEBA@@HADBDBF@DAFAFEL@DFJBHAHCD@B@FABE@CAEFAB@DDH@DADCDEFCD@DAF@BABGDIFAAA@AGC@CFAD@RBB@DIFADKDAD@F@@HF@BC@EBG@EDADAJEHGFEDMDCFAB@H@FHFBDAHALGJEFC@AAGCA@EDABAHBNBPDFBDBBAFAD@DADCBM@CBGFCHGPCBC@GEGAE@CBCDABCFKTAFAFCDA@E@CCGCEAG@GBGFIHGJGBK@cCMCMEKCI@GAKCOCQAKEI@Q@OAeAI@EAA@BAJKHEBABC@GBEBCDCFEBABG@AAE@C@GBCCGAAAK@MAGBCF@L@BABE@IBCDAACCEACAIBGDEAAGGGCCAIAGEAC@O@CCGCC@ECGGECCCAIAECCEACECGEIIEKAEAE@AAG@GACEIBE@AEEAGAGEQCK@AGGCCCCIEAC@E@CFC@AGEAC@CBADC@EACIKCEAEBEAAECEKCAE@C@E@A@EHEDE@CCCCGICE@IACCCE@IAGCGAIBEDA@EAAAECEAEBC@GDADGFGHCDCDCBEBC@I@EAAA@EC@EEA@GBCAECCAECC@QBAABM@KBCBCFCHIFCFEJUFEFCBC@EAICEAC@EBICIBCBCNIBCBCBCBC@EAGAECAGAIOAACCLDJ@NAFABABGDIHMBCFKBEDCFGCACCCCGCIEGGEIGGEEAAE@AA@ESMw@QEWD_B@]CU@WBSFAKBKBUCI@OIQ@E"]],"encodeOffsets":[[[102242,24806]]]}}]}