{"type":"FeatureCollection","features":[{"type":"Feature","properties":{"adcode":532530,"name":"金平苗族瑶族傣族自治县","center":[103.228359,22.779982],"centroid":[103.095706,22.776325],"childrenNum":0,"level":"district","acroutes":[100000,530000,532500],"parent":{"adcode":532500}},"geometry":{"type":"MultiPolygon","coordinates":[["@@C@MFEBCBOBEB@AEEAE@CDE@A@G@CECEEAAAABEHKCACCECCCACCG@C@AGGCGAGACCCCEKMEEBEDEBAREHCBC@EAEGCCACBMFG@E@EAC@MBKBG@E@O@EAGACAQGICKCCCAE@CACACCCECAABEBCHEHCF@FCJCJALCFADCFALELEDCHE@ECK@AAC@EDCJEDCBE@M@AAG@EBGDC@AAEECCAAAEGCAAG@M@ADIBEAECCECGAEBEDCF@BGHAEAAEGEAGEAEACIEAAC@@JEHKLOJSDC@MEGAEAGAGAABEDADAJDH@D@FELENAFGPEDGJGNADGNAH@NABE@CBBHBFCFCBABG@KF@BGFOHEDIFEFAD@JCDBFDDBDDBDDAHCFGFIHGFIHCDEFEHEDCBC@CBK@EBABMDEAEIA@ACAAE@CBG@AAAADC@ACCE@G@GAIDI@C@GBEBC@GFCDBB@BBD@BGH@DBJ@HABADEFCBCBEDADC@G@C@ECICG@GFCBCDCDCBC@CACCGCCGCGCCACBCEI@E@MAEBE@CAEGAEAGGEGACAGGIEEGGCAICE@CCCABCFCBABCFAFI@CBA@A@C@A@KBCAACBA@AAKCOBCAC@A@ACC@E@CACAAAEAAEEBCAEAAAA@AAEC@ACAGCE@BC@G@CDGDCHEDEFAJANBBABA@CBIDEDCFADALGDEDADCFE@G@EAAE@MCAACCCGAAACGCGAECCAEAGAI@K@C@GDGHEJ@BADCHCBKCGCG@C@CBGBABGDABMFK@CACEICQAIDGFCDILKLCGCEAG@GAEEK@MAGAC@GDE@CCECCAEAEACAC@GC@AACB@BEB@BA@CAA@@DE@DCCA@AEB@@AEIAEDEAA@CBE@ADGACDEC@ABCD@@CGCAA@EACAAAC@AGEAEGEAAACABCACEGECAKCC@EDGBIACCCAEAC@KCAAJEFCFEBCHIFAFBDADABCCC@C@IDCDAFCFCJMBABMFSBAFBFBJ@FBDHBBATDFDDFBHFFFDBJ@HEBADEPKBCLIJGD@JKDCFAHEFADCBEDCB@FBBBHDHDLBLDHDHBF@XIDADADEBC@E@GBCLCDADCJABAFIJCD@F@J@LBDABABGBEDKBAHGJALAH@L@HGBAAAEK@AJMDCHCHAF@D@F@LBFAHBFBDBHAFADAFAFCD@BABKFCHAH@LAFADCDKBCDALCFCBCDEAGCECCAAAGBCD@HGHE@AGODCFEHADCHEBABCEECGBENIJCHEBC@C@EBCBEBEFCH@HABA@CAGDIBCBIDCDADALDF@LCFADBDBF@DABEDCDAD@HBD@H@RBD@DCDCDCBACGAGBAFCH@F@HAF@BAFCDGDCHAFCFGHCDADBHDF@N@B@F@D@LJF@FCFAH@LBDDDL@B@L@LADCDGFCBDJBFADCBADJLFTDFDDFBHBD@HBFBNDF@NFFBJHJFJFFHFLDBFAD@FBBBDBDAFAD@DFLHHFFBDBDBHDDDBFIJKJGLEFCHCHAL@FBFD@@FBD@FDDAFHLDFJN@DBBF@D@DB@D@D@DBHDHBBNJB@DALCHAH@H@L@LDBBDJDDDDJDDDDFJFDBHBTBHDDBNHFDFBDF@HCJBJBFBHFFDBCFAD@DBHADAL@FBHFHHNDDFFDDFLLFDFHXFJFBAN@F@F@N@H@DDFBDJATGJAR@F@JCJALCJCNKFCBABCDIDAD@D@FAD@TCLEB@BG@CBCFIDATEJCFADEDA@G@EACEEAACAIEAC@S@G@GDG@EBC@KJIBCJEDAHGHCHGBAAMAC@K@GBEHIFGDCHEFADCDIBCDELKDGDCFCNEBADAHCDC@CAC@CDADAHCNCJCF@D@DDDHHJBDFFDHBJBFDFDFDP@@JDVFBBDD@FDJHXBJADQRCHCHBBAN@LBDJRBDBDHNDDF@@F@DBBFFHDDFBBHFBFBFB@HFFDBHFBBBAJ@DDDJLD@DB@FCL@FBBFAHDHF@AFCDAF@B@EJD@BD@DBBB@BCBADBGFEFCDCDEFGHMJIHCFABADCDC@O@GBA@CD@FAF@BDDBF@BABKLABEBG@KCCAC@KHADCFANCDBDDDAD@BGFCFIHCBGDEDCDEHEFEBGFGHCDCDEDIBGFEBEFABABE@CEC@EBCJCH@DADEDEFGDIDCACCE@CBEDEDGFCDEHEJCDAFC@C@GAEBEBMJEF@BKLAD@BADCDI@CBADBBFBBDABEBEFEBCBGBGFCBGBABEAIDGBMJEDCDADABCBA@CAA@GDCDCBABE@E@EDG@EBGHCDCBE@ABMDGDA@EHCBG@E@A@CFCHABIACBADADIBIDMHEDCDEBEDC@"]],"encodeOffsets":[[[105724,23620]]]}}]}