{"type":"FeatureCollection","features":[{"type":"Feature","properties":{"adcode":540622,"name":"比如县","center":[93.68044,31.479917],"centroid":[93.48801,31.4412],"childrenNum":0,"level":"district","acroutes":[100000,540000,540600],"parent":{"adcode":540600}},"geometry":{"type":"MultiPolygon","coordinates":[["@@KDQFIPMPUJYDWFY@SJGN[H]@YC]BSAKGCOMIkDuDWBUAQBQAcDOLQRMJWJUPKR@LFHCLILGJKFQDYBQBYFUJKBM@OBQHIHEHILKHIHGBCFGHCNGLM@GDBHIFGAIDGAEEA@AJCBQBEAG@EDG@EBWFEACBYFE@IFW@MBMDGHKBQCK@EEGAMD@AJGACMBE@GCAA@MCEECWSEEDOJCBE@ECG@EBGAEUAOAI@CFIBK@KNKJCFAJAHAD[FOHEJBHDD@FEBSBIBEFKDE@cUSGQMCEHQCMCKBOCGEI@MCEIECILMVSDAHE@EFGHAAECEAGCCGAKAU@IAIEEICIEGMIKEOBGCEEEGA@BH@FBJABIAGBKLIDILM@GDC@CEQKGAKAEAEUGI@GFE@EAGAIBIBE@EGEM@EACGAMKEKCKEEBSFIBIGGI@GBEB]F@TAHEJIDAPCZGLETCVILGPGF@VIBCFIJKJCN@XAFDDDNEFLHHHBR@HBDBBLBFLFNNNFPNBDJFLBPFXHJBLGFGBKLBFAJCDBL@H@EEICECGGMcHGHCNFPAJALMNEFEGGIIAC@MCIJCFGHCHAJEHCDIDKBGDEBKJKl[ZIXMZKVMVKRCRCRGDUIUOUKMQCoHQEQQCMNOVGRKEMMUSYG_GOOCKAUHKJMHU@OGQOM[IiBMLKVCZ@`ARHLELO@[PO^G`MbGZObK`E^AVAPMDUEUAUIMQKYMEQHI\\cLYJuAWKUIKIKHMAMAGDCHWPYDIAODEFKBGAGDG@CFMDM@GBI@EFBJLJBBCCEFGAIBEEE@GDEACKQ@CFBXABAOICEWQIGCEKGBAT@DDH@FCH@JDH@FAFDH@RBDAFD`ALBPFJBN@HFFALAHBDAVDDBL@L@TDDAH@P@NEJBJANICEJGGEEACCT@J@NCFERCJINCFENGNIF@HCRCRDTAJCbC\\EdKPAHBBKIACCEIICCEMC_AWMMSOKFO@_HM@cZQTJXHVJFZDLpFLJNJtALJHRJHT@T@ZIVKTGNIRMVMTKZEV@`KTANKNMLQV@\\@ZGBUBQTGPITBFKBSJDX@`@RJRFLGLKVGTCLFPQLGLCTClGfATLRDNGTC\\JLG@KFKNC\\ARIJKJMLMXaRCXCVEXBFJHHTDNN@\\LTNIPAPCT@XDTCT@P@TETCrERIVETCVInHRJPLLJPBPER@dJV@NKVSZCXGTE\\@THHNBVDRLXBRJPHXKLcRKPKZEZAZMNQNOVONMTKlCVAZCTKPWLOBUDKRNpJVJ`NVHTFXHVZN\\HRHNFHLCTMVCZBXBRHTJXNHAJ@JELBHDJ@DEHBPBPHTCHSPMFCJAFcLY@]@UGQEWCWJYBoEYIY@Y@YFULMBBJCJ@JBHJFFJHHDPCLCFIHCHEFGDM@EAG@KHGHEHCHMGG@GDC@CFEDILEVEBUBIBGDEG@UEAKAEBAHELCNKNEJEHKLGCONKPcZSFQA}AOJIPGNObOLQFM@OBMHKRWZMX@VCXMdKVMVQRQTMPMRULO@KICMBSCOMUYEYBUDMP]bOLOAOCKHINDPT`HTPbN\\HNFL@LM@OAMDORUZKHOP@PFLPTKNUDUAWDeNQHOLMXEPARGN]P"]],"encodeOffsets":[[[95753,32684]]]}}]}