{"type":"FeatureCollection","features":[{"type":"Feature","properties":{"adcode":610502,"name":"临渭区","center":[109.503299,34.501271],"centroid":[109.557917,34.548377],"childrenNum":0,"level":"district","acroutes":[100000,610000,610500],"parent":{"adcode":610500}},"geometry":{"type":"MultiPolygon","coordinates":[["@@KJEJCLIX@D@FBNALAHAFCFGDIBGFA@I@GDCDCD@DCFABDH@BC@EAACAKAGCCGBAB@DDFDDBB@JBF@BBBJ@BBBDIPADINAH@H@@GBADELKLMV@F@HBFBDAFCLEP@F@DNZBH@LAFEFBJDL@FADDRBJHJDHNJHDHBDDBDDLBFCL@H@BGJ@HBDAD@DBDAF@FHLBH@NFDDBDBBF@DCFCDAH@BBFHHDDBDBDBDB@DABAHCF@H@DB@BBJBDDDFBH@F@FABA@AACAAE@EA@AAADAHAFAD@HDD@F@F@FAB@B@FNF@B@FDDZBT@NCPBN@FHF@BBDAHALAZ@DBH@BHFJDDFBHFVFVNnZ Pb_AEACAECEGIGEAE@GAI@MBQDGDE@K@A@MEEAMAABIBEDCDCJCBG@QEWIaSKEACCE@C@GBEQA@BG@@FE@@EMAAFC@@FCA@DE@@BQAAFG@EDGDEDCBIJADABG@EBIACBCBCBADABGBGAI@I@E@IFCBCDEDGFKDE@CACCCEKGMAICCECACEAAO@C@ACGCO@mED]@ABGAEDCFCBCBCDOBGFEDCFADA@CCAGCCEAC@E@GFIBEHCDC@AAAECECAA@C@EBWFWBEBIDQF]@GAE@CBCBCBEBI@G@CVB@BK@EEBE@MEOCCCEGGICCKAGAIAC@A@EDC@AAGKBIBGBEBI@CBCNAH@FEBABCACC@GBE@CACCCEAECGEIAC@G@EBEBEDCFAD@HAFBFADAHE@ABE@E@CBAPIBGACEEBADABA@CAC@C@C@EDCFCJELAHAFIBE@GAE@EDAHADAL@D@@CFCA@E@BCACBABA@BF@@CA@@EA@CCDCA@CABABECAAADC@CCCAA@CCAACB@ACBA@CB@BC@@AE@AAA@ACABAA@@CBACABA@CCABAAABAC@BCC@@AB@@AACB@BC@ACABC@AB@BAA@@AB@@ABA@EFABAAEAC@EACBC@ALAF@FCF@AAB@BBDBBD@@AGBB@AB@@BBBACD@ACBA@ADADBDAAAB@BBBACADA@C@A@@B@FIBCFEDEFADAJANEFAHEDCFGB@F@DBFDDBH@JALAFBFBBBHHFAHCD@LBB@HCBATGJADAJELCJAFCDCJCJCPCBBJHHFHBF@F@F@BAJGJEL@NBNFF@"]],"encodeOffsets":[[[112324,35065]]]}}]}