{"type":"FeatureCollection","features":[{"type":"Feature","properties":{"adcode":610632,"name":"黄陵县","center":[109.262469,35.580165],"centroid":[108.945565,35.6228],"childrenNum":0,"level":"district","acroutes":[100000,610000,610600],"parent":{"adcode":610600}},"geometry":{"type":"MultiPolygon","coordinates":[["@@QFCDBBBBF@NAD@BB@DABCBIDAB@FB@D@PBFBBB@DCBABCAICE@E@ABAD@BDBF@H@D@@BADIDABADADAHAH@BCBC@C@OEA@ABBFADADABC@C@CACEGEACC@CBAB@FDV@DAFABCBC@KACBGTA@E@GAG@A@ALABEDAB@D@BDDJHBBJDBBABEBEDGJEDA@C@CCCIAACAI@CBCDABBBBDFDFDBB@FAJBFBBFDFD@DADADCBG@I@IBCBAD@D@BFDJB@DGNAHBH@DAFKTADBDBFFD@D@F@T@FBHBDAHBF@BAFAF@DGHADAF@BCBILIJILCDAD@FABCBADAFCFI@]HG@CCIEEAECGIAIEqACE@EBoJCDIBG@GAEEG@kLcPCLA@AFDJ@DABC@EAEGESGCMAOBAB@DJJBBDFHFDDABC@CDG@CBMBKASMCKAgEQ@CEAEBQNIHobEBKFIBC@[IG@AB@DBRAFEFMDADABIBK@UNeTMDULUJQDSHLU@SGICcSWESSUOKGOOWGeG[EaCw@iBK@eKU@YEIAK@cQ@CAGEEEAUHEFEFGBSREBG@AACECCAAAAEEAAA@EBED@BIFCBEJABCBEAKEGEGCC@EAA@K@G@@AC@BCAACCAA@G@EAAGKGIAAE@AA@A@EBCJEFC@AAGACCCEE@A@EDGDCDCHABCBABGACA@AE@CEICMFS@KHSDK@A@CHG@CDA@EBKBKNIDAD@LAHBDADABEDEBG@EBAF@B@FAHGF@B@FCHGLMJERABCDCLCBCDGAODEFFDBB@FGFAF@FBFDDBDCAEBIBADAJFHFB@F@HGD@CE@GJABABEB@HBBC@E@AGMBCB@FBF@BADEB@F@BBBDFFDBB@JAJCHCDBLCDAHBD@DABCLOLGdEPCNMBUBSJQNIHO@Y@EN]FMFEHI@C@CAACCA@CE@CBCDAB@LBFAPBPDH@BABK@CAE@CBAL@BADA@AACBE@MBCFAH@F@DADABCDAFDD@BCFHJFJBB@FAHAR@DDB@LFHHDBJ@FDFBNPHJDLBHFJHFPJNLFBD@BBBD@FAH@@RHDDBBAJBBNLHF@BIJEDADBD@BHFHFBBBLBFFD@B@LDHFHHLBDNHHDDF@HAL@DDBL@FBFDBD@DBBHADB@BADCL@B@DNLBBFBJFFD@LDBFBFAD@RGF@FANBF@HCD@BBDBDFDFFFBBRFFDBB@FBDFBD@JADBB@FHBBDBD@NAJ@H@FBDDF@FDBBH@LDNBP@F@HAF@LBDADCHIFKFEBG@CAADGDCBBFDDBBCAKDEVcHEDAL@^GX@P@FDJAH@D@HCD@HDD@H@D@HAJAHAF@DBLHDBR@L@F@FABAFADA@@FDB@FDD@LAN@HAF@HBFAD@DC@CBCACCABADAF@DCDELEDALAD@BDDHBDHDDBP@"]],"encodeOffsets":[[[112076,36364]]]}}]}