{"type":"FeatureCollection","features":[{"type":"Feature","properties":{"adcode":620602,"name":"凉州区","center":[102.634492,37.93025],"centroid":[102.753191,37.912189],"childrenNum":0,"level":"district","acroutes":[100000,620000,620600],"parent":{"adcode":620600}},"geometry":{"type":"MultiPolygon","coordinates":[["@@IDIBWKQEQKOIEAMDEDMLaLQNGHQLOHeTID»¢ǟDĥFK@eB_@_TASEG@EJDH@FEFBHBJADBJC@CEEAG@ACFE@CGCC@CE@EEE@C@ICACEAECAMMCICCGBGEC@CAG@ACCAIBGDQB[@OBMAEBKDSJIBGBGFGBCDMAKBI@CBCAIAKDIAUHABCA@FGBADIBEDECGBCAGBIACGC@GEAEA@CGE@@CMEQ@@CICAEKK]SCCWIECWeGCKCKAYBG@EDCD@HADAJDFGDGJEDSJKBEAI@]FQBO@KCMESEQCOEWAMAKASEaGICKAEEWCGACCFCLEEIISKKCEAOCGI]CGCAGBAHIEC@EHCDCBGGCBCCFAEGGCABAFCDGDCFC@OMCAUEEAEICAGAKFIGI@ACIFACGAACEAAAICFCF@JLHCDAHA@EKKBACI@EDIDCPANELArDNALCBIGIGCSGMGI@GCKIKGWGMEMKGEKEGASEKAaE]EOECGBCLEVATAdCJAPOPCLDLCN@FANEHGDM@EEMEEAEDIFETKNOBEFMHKPIFALAFBXJXDPFDC@EJDBEJCP@DBBFHBFLFHNDP@NABBBHD@R@HADANFHBN@JBRBLAF@HFDHD@LEJDDCJ@JGBEBAJBDJBHNDFDJBFDTFFBDFDFLDD@JIJA@EBGDAJAPANAXGHCHGBKBEBICGS@EGDGDCDGBGDABGFA@EDEDMBICEGCOAICEGGCEGF@JFPNF@DABIBC@ECEBCHAFAHABG@ECERMCEDGKKGAGGDEJ@BEAEPIPGDFTLPHPBFDB@DG@OEOZKBIDCJFHFLBJGFMHE@EGCACKKACDEFADAAIBCHBJBJADCECCEIEI@GE@AH@@EECEI@CDAHAP@LDFDFH@HHDHEBBHFPDBF@FDJDDFGJ@JFD@@GBCPALBFADE@ENQBGDCFGBGAEBAZDHDD@JGJMHEFAJIFG@CEIBMEKBEMCECEDKGEGEKBQDGDEHK@AGAOIMEAIEASJEBSACFCDE@MCUWEAMEQAG@GFEDAFEJKBGAEEAEDGDEHANALG@ILW@CAGGG@EBEDODAD@FCNOFCHKJEAKCIDCG@EEIIJKFEF@JN@FFHDBFCDGJYJIJKFCNCVAXEBI@EGEECACFIFCBOBED@HFF@JALIBBDJGHALBFFDFCBA@GLFLDHBdPPHFE@IBGFEDGFEB@JDFHHPHHLTDFADGDEJALDHBDPJBD@JCR@HJVHJ@LPJBHFFFFPRBH@HFCHDHNPRHHRVDFB@NRHJLNNTFJPPDHLHBD@XAL@BJFDHBLFJ\\ZFDXDFBLF\\BLDDDDFJHLBXARGL@NBFF@JFZBDHD@H@DgPOrBR@\\RBjDºTPFPDNFNHLFLBZJJDRHbNRFRHHDPJLDXLJLLBVHZLJDJFTJVJJH^PVH\\NJD\\JfTHFbPHDjRNDNBCPE`CHANERKPCBCDAR@ZDLBHCXERENAL@FDVBZ@PDRBFBD"]],"encodeOffsets":[[[105851,39004]]]}}]}