{"type":"FeatureCollection","features":[{"type":"Feature","properties":{"adcode":654301,"name":"阿勒泰市","center":[88.138743,47.848911],"centroid":[87.917843,47.884663],"childrenNum":0,"level":"district","acroutes":[100000,650000,654300],"parent":{"adcode":654300}},"geometry":{"type":"MultiPolygon","coordinates":[["@@SHHEHgTQFYRYXSJSHIBAnBRDdD`BZBV@xBJCLDZFN`dXTBVFFCDFRDJCHDJXLPLP@RFJLHDTZFVCLPTFLBTDFDPLFBLXhJXPZHR@JPNPR`TV@NHJL@JENBL\\NNVM\\B^RD\\@NDN@JChCXJJ@PC^@HFQ@AHEFMCCFOBCBWB]NMCADVVBNAHHPAJGFYDEHYJ@F\\PERBFTHH@KNO@YFSLBPKJSDIHaHQ@SAGC_DUCaD]PUL_JGFAVHDPBPPRNJBLHZLFFBJfRPFR@LDRP@HOR@XAJMRKTAJLhAP@XHRHF`VdPbHRJHJVHHLJDJHXDHNNBRFV@\\FJPL@LLIJG^QPcPOT@LDL@LENCRIJ_ZANR\\RRVZJTAPKJ[JYJAJBZuCWBMFGJCxSLSFYE_WYKWAM@KFQLUNdgRGN@PLZCDWJYJODUH£\\OJWBW@OBMLKAKG]KUHabcXQFIAOKMHELOVGHOD]@wCcDw^OF]FeNUXCHBPlZbFXHOFIHK@IRKLQFQAICKAaDEDO@QEO@UNSAIEEIKEUIEEHGFUOUKQ@QCGKIWG]OOQOMaIiCWCkCGE_KCMYEUBUCMWAMIQCMUC\\OXSTQDIDUB_IQYU@EMEYQKU@MEkEKOGMC]BOAaBME@CJEXQNCPEDIGECOIEFI@OJIBGM[@IDGBKGMKEGMOIAGDE\\CPGHHBEGEMAEMSDCAHGYQWCKMWGIGYBIATSCKOOGCUMDM@IDKTaDQEEDIAIOQNOFSbOLEBCKEUSUMOGQAKEYGWC[@KC_CAETIKGCEOKGGSIIIFGTKLMHGDIAIDQMM_GYMSCOQGCBMDOEEBIGKaCQEUKMKI]H]LOEUDQJMPMCKYIMUmGO@oKWKYSiUcEWQ_KCCM@KGAEF@JIBAKIAJCBCIIKDBCPEECUHIAGJI@DHMA@EQCQ@@FHJCDMAKDCF[AIAWJQAGEEIA_EEOCENPNBHEBOCK@KKeF[LUBOIKDMPEDQA@JMASBGAug_SYSu_eaoiuUJAlM¨mj[HGJONI@OLCBUCIHODO@GKYMGQSIMAINBlL`JpRxPP PPDZ@ZJjHZJ\\HXHlThJVDJXDFH~JD\\C`@PCvBPAjBPB`IPGBENDLAHE@GIWKOLLPXJO@MCOOUMQQMCIIER@ƈ@²@BOPA@hMHKCMFOPNNVMJDZBBEJADHHBFC@IFEJ@XSPDFAEOR@FHNAHNNARMGEPKJ@GIQF@CWAqL@]LENKFEJC\\K^PTH@TNDZ@rMJEQ\\K`@XAVE^Ar]VI^ITMfG¤]RG^EUKfH`DHDJTNDRWRITCtBdBfL\\BPHPL"]],"encodeOffsets":[[[90553,48393]]]}}]}